[
  {"id":"ch-001","clientId":"client-001","type":"inbox","name":"Внутренний почтовый ящик","description":"Встроенный почтовый ящик приложения","status":"active","config":{},"rateLimits":{"perMinute":100,"perHour":1000,"perDay":10000},"stats":{"sentCount":15234,"deliveredCount":15234,"failedCount":0,"lastSentAt":"2025-03-20T12:00:00Z"},"createdByUserId":"user-001","createdByName":"Maria Admin","createdAt":"2025-01-01T00:00:00Z","updatedAt":"2025-03-20T12:00:00Z"},
  {"id":"ch-002","clientId":"client-001","type":"email","name":"Email (SMTP)","description":"Электронная почта через SMTP","status":"active","config":{"email":{"smtpHost":"smtp.wealthos.example","smtpPort":587,"fromAddress":"notifications@wealthos.example","fromName":"Wealth OS","replyTo":"support@wealthos.example"}},"rateLimits":{"perMinute":50,"perHour":500,"perDay":5000},"retryConfig":{"maxRetries":3,"retryDelayMs":60000,"backoffMultiplier":2},"stats":{"sentCount":8956,"deliveredCount":8890,"failedCount":66,"lastSentAt":"2025-03-20T11:30:00Z","lastErrorAt":"2025-03-19T15:22:00Z","lastError":"SMTP connection timeout"},"createdByUserId":"user-001","createdByName":"Maria Admin","createdAt":"2025-01-01T00:00:00Z","updatedAt":"2025-03-20T11:30:00Z"},
  {"id":"ch-003","clientId":"client-001","type":"sms","name":"SMS (Twilio)","description":"SMS через Twilio","status":"active","config":{"sms":{"provider":"twilio","fromNumber":"+74951234567"}},"rateLimits":{"perMinute":10,"perHour":100,"perDay":500},"retryConfig":{"maxRetries":2,"retryDelayMs":30000,"backoffMultiplier":1.5},"stats":{"sentCount":234,"deliveredCount":230,"failedCount":4,"lastSentAt":"2025-03-15T03:25:00Z"},"createdByUserId":"user-001","createdByName":"Maria Admin","createdAt":"2025-01-01T00:00:00Z","updatedAt":"2025-03-15T03:25:00Z"},
  {"id":"ch-004","clientId":"client-001","type":"push","name":"Web Push","description":"Push-уведомления браузера","status":"active","config":{"push":{"provider":"web-push","vapidPublicKey":"BEl62iUY..."}},"rateLimits":{"perMinute":100,"perHour":1000,"perDay":10000},"stats":{"sentCount":4567,"deliveredCount":4123,"failedCount":444,"lastSentAt":"2025-03-20T10:45:00Z"},"createdByUserId":"user-001","createdByName":"Maria Admin","createdAt":"2025-01-01T00:00:00Z","updatedAt":"2025-03-20T10:45:00Z"},
  {"id":"ch-005","clientId":"client-001","type":"slack","name":"Slack Integration","description":"Интеграция со Slack","status":"active","config":{"slack":{"webhookUrl":"https://hooks.slack.com/services/xxx","channel":"#wealth-notifications","botToken":"xoxb-xxx"}},"rateLimits":{"perMinute":30,"perHour":300,"perDay":3000},"stats":{"sentCount":1890,"deliveredCount":1885,"failedCount":5,"lastSentAt":"2025-03-20T10:45:00Z"},"createdByUserId":"user-001","createdByName":"Maria Admin","createdAt":"2025-02-01T00:00:00Z","updatedAt":"2025-03-20T10:45:00Z"},
  {"id":"ch-006","clientId":"client-001","type":"teams","name":"Microsoft Teams","description":"Интеграция с MS Teams","status":"paused","config":{"teams":{"webhookUrl":"https://outlook.office.com/webhook/xxx","tenantId":"tenant-001"}},"rateLimits":{"perMinute":30,"perHour":300,"perDay":3000},"stats":{"sentCount":567,"deliveredCount":560,"failedCount":7,"lastSentAt":"2025-03-10T14:00:00Z","lastErrorAt":"2025-03-10T14:05:00Z","lastError":"Webhook URL expired"},"createdByUserId":"user-001","createdByName":"Maria Admin","createdAt":"2025-02-01T00:00:00Z","updatedAt":"2025-03-10T14:05:00Z"},
  {"id":"ch-007","clientId":"client-001","type":"webhook","name":"External Webhook","description":"Внешний веб-хук для интеграций","status":"active","config":{"webhook":{"url":"https://api.external-system.example/notifications","method":"POST","headers":{"Content-Type":"application/json"},"authType":"api-key"}},"rateLimits":{"perMinute":20,"perHour":200,"perDay":2000},"retryConfig":{"maxRetries":5,"retryDelayMs":10000,"backoffMultiplier":2},"stats":{"sentCount":345,"deliveredCount":340,"failedCount":5,"lastSentAt":"2025-03-19T16:00:00Z"},"createdByUserId":"user-001","createdByName":"Maria Admin","createdAt":"2025-02-15T00:00:00Z","updatedAt":"2025-03-19T16:00:00Z"}
]
