[
  {
    "id": "recon-001",
    "clientId": "client-001",
    "reconType": "ibor_vs_abor",
    "scopeType": "portfolio",
    "scopeId": "portfolio-001",
    "asOf": "2025-02-03",
    "breakAmount": 0,
    "currency": "USD",
    "status": "ok",
    "relatedIssueIds": [],
    "notes": "Full reconciliation complete",
    "createdAt": "2025-02-03T08:00:00Z"
  },
  {
    "id": "recon-002",
    "clientId": "client-001",
    "reconType": "bank_vs_gl",
    "scopeType": "account",
    "scopeId": "acc-jpm-001",
    "asOf": "2025-02-03",
    "breakAmount": 0,
    "currency": "USD",
    "status": "ok",
    "relatedIssueIds": [],
    "notes": "JPM checking reconciled",
    "createdAt": "2025-02-03T07:30:00Z"
  },
  {
    "id": "recon-003",
    "clientId": "client-002",
    "reconType": "custodian_vs_portfolio",
    "scopeType": "portfolio",
    "scopeId": "portfolio-002",
    "asOf": "2025-02-03",
    "breakAmount": 15234.50,
    "currency": "CHF",
    "status": "break",
    "relatedIssueIds": ["dqi-012"],
    "notes": "Bond price discrepancy",
    "createdAt": "2025-02-03T06:30:00Z"
  },
  {
    "id": "recon-004",
    "clientId": "client-001",
    "reconType": "ibor_vs_abor",
    "scopeType": "portfolio",
    "scopeId": "portfolio-003",
    "asOf": "2025-02-03",
    "breakAmount": 5678.00,
    "currency": "USD",
    "status": "break",
    "relatedIssueIds": ["dqi-005"],
    "notes": "GL entry timing difference",
    "createdAt": "2025-02-03T08:30:00Z"
  },
  {
    "id": "recon-005",
    "clientId": "client-003",
    "reconType": "bank_vs_gl",
    "scopeType": "account",
    "scopeId": "acc-barclays-001",
    "asOf": "2025-02-03",
    "breakAmount": 0,
    "currency": "GBP",
    "status": "ok",
    "relatedIssueIds": [],
    "notes": "Barclays UK reconciled",
    "createdAt": "2025-02-03T07:00:00Z"
  },
  {
    "id": "recon-006",
    "clientId": "client-004",
    "reconType": "bank_vs_gl",
    "scopeType": "account",
    "scopeId": "acc-dbs-001",
    "asOf": "2025-02-03",
    "breakAmount": 2345.67,
    "currency": "SGD",
    "status": "break",
    "relatedIssueIds": ["dqi-032"],
    "notes": "Pending FX conversion",
    "createdAt": "2025-02-03T02:00:00Z"
  },
  {
    "id": "recon-007",
    "clientId": "client-005",
    "reconType": "custodian_vs_portfolio",
    "scopeType": "portfolio",
    "scopeId": "portfolio-005",
    "asOf": "2025-02-03",
    "breakAmount": 0,
    "currency": "USD",
    "status": "ok",
    "relatedIssueIds": [],
    "notes": "IBKR positions matched",
    "createdAt": "2025-02-03T07:30:00Z"
  },
  {
    "id": "recon-008",
    "clientId": "client-006",
    "reconType": "custodian_vs_portfolio",
    "scopeType": "portfolio",
    "scopeId": "portfolio-006",
    "asOf": "2025-02-03",
    "breakAmount": 0,
    "currency": "USD",
    "status": "ok",
    "relatedIssueIds": [],
    "notes": "Northern Trust custody reconciled",
    "createdAt": "2025-02-03T06:00:00Z"
  },
  {
    "id": "recon-009",
    "clientId": "client-007",
    "reconType": "ibor_vs_abor",
    "scopeType": "portfolio",
    "scopeId": "portfolio-007",
    "asOf": "2025-02-03",
    "breakAmount": 45678.90,
    "currency": "USD",
    "status": "break",
    "relatedIssueIds": ["dqi-028"],
    "notes": "Swap MTM timing",
    "createdAt": "2025-02-03T07:00:00Z"
  },
  {
    "id": "recon-010",
    "clientId": "client-001",
    "reconType": "bank_vs_gl",
    "scopeType": "account",
    "scopeId": "acc-jpm-002",
    "asOf": "2025-02-03",
    "breakAmount": 0,
    "currency": "USD",
    "status": "ok",
    "relatedIssueIds": [],
    "notes": "JPM savings reconciled",
    "createdAt": "2025-02-03T07:30:00Z"
  },
  {
    "id": "recon-011",
    "clientId": "client-002",
    "reconType": "bank_vs_gl",
    "scopeType": "account",
    "scopeId": "acc-ubs-001",
    "asOf": "2025-02-03",
    "breakAmount": 0,
    "currency": "CHF",
    "status": "ok",
    "relatedIssueIds": [],
    "notes": "UBS CHF reconciled",
    "createdAt": "2025-02-03T06:00:00Z"
  },
  {
    "id": "recon-012",
    "clientId": "client-001",
    "reconType": "ap_vs_gl",
    "scopeType": "module",
    "scopeId": "ap",
    "asOf": "2025-02-03",
    "breakAmount": 1234.56,
    "currency": "USD",
    "status": "break",
    "relatedIssueIds": ["dqi-011"],
    "notes": "Vendor invoice timing",
    "createdAt": "2025-02-03T09:00:00Z"
  },
  {
    "id": "recon-013",
    "clientId": "client-001",
    "reconType": "ar_vs_gl",
    "scopeType": "module",
    "scopeId": "ar",
    "asOf": "2025-02-03",
    "breakAmount": 0,
    "currency": "USD",
    "status": "ok",
    "relatedIssueIds": [],
    "notes": "AR fully reconciled",
    "createdAt": "2025-02-03T09:00:00Z"
  },
  {
    "id": "recon-014",
    "clientId": "client-001",
    "reconType": "ibor_vs_abor",
    "scopeType": "portfolio",
    "scopeId": "portfolio-001",
    "asOf": "2025-02-02",
    "breakAmount": 0,
    "currency": "USD",
    "status": "ok",
    "relatedIssueIds": [],
    "notes": "Previous day reconciliation",
    "createdAt": "2025-02-02T08:00:00Z"
  },
  {
    "id": "recon-015",
    "clientId": "client-002",
    "reconType": "custodian_vs_portfolio",
    "scopeType": "portfolio",
    "scopeId": "portfolio-002",
    "asOf": "2025-02-02",
    "breakAmount": 8765.43,
    "currency": "CHF",
    "status": "break",
    "relatedIssueIds": [],
    "notes": "FX timing - resolved next day",
    "createdAt": "2025-02-02T06:30:00Z"
  },
  {
    "id": "recon-016",
    "clientId": "client-001",
    "reconType": "tax_vs_gl",
    "scopeType": "module",
    "scopeId": "tax",
    "asOf": "2025-02-03",
    "breakAmount": 0,
    "currency": "USD",
    "status": "ok",
    "relatedIssueIds": [],
    "notes": "Tax lot cost basis matched",
    "createdAt": "2025-02-03T10:00:00Z"
  },
  {
    "id": "recon-017",
    "clientId": "client-005",
    "reconType": "margin_vs_broker",
    "scopeType": "account",
    "scopeId": "acc-ibkr-001",
    "asOf": "2025-02-03",
    "breakAmount": 0,
    "currency": "USD",
    "status": "ok",
    "relatedIssueIds": [],
    "notes": "IBKR margin reconciled",
    "createdAt": "2025-02-03T07:30:00Z"
  },
  {
    "id": "recon-018",
    "clientId": "client-007",
    "reconType": "margin_vs_broker",
    "scopeType": "account",
    "scopeId": "acc-gs-001",
    "asOf": "2025-02-03",
    "breakAmount": 12345.00,
    "currency": "USD",
    "status": "break",
    "relatedIssueIds": ["dqi-013"],
    "notes": "Margin calculation pending review",
    "createdAt": "2025-02-03T07:00:00Z"
  }
]
