[
  {
    "id": "conc-001",
    "portfolioId": "pf-001",
    "type": "singlePosition",
    "name": "Apple Inc (AAPL)",
    "identifier": "AAPL",
    "weight": 8.5,
    "limit": 5.0,
    "status": "breached",
    "marketValue": 4250000,
    "asOfDate": "2025-01-15",
    "createdAt": "2025-01-15T08:00:00Z",
    "updatedAt": "2025-01-15T08:00:00Z"
  },
  {
    "id": "conc-002",
    "portfolioId": "pf-001",
    "type": "singlePosition",
    "name": "Microsoft Corp (MSFT)",
    "identifier": "MSFT",
    "weight": 7.2,
    "limit": 5.0,
    "status": "breached",
    "marketValue": 3600000,
    "asOfDate": "2025-01-15",
    "createdAt": "2025-01-15T08:00:00Z",
    "updatedAt": "2025-01-15T08:00:00Z"
  },
  {
    "id": "conc-003",
    "portfolioId": "pf-001",
    "type": "singlePosition",
    "name": "NVIDIA Corp (NVDA)",
    "identifier": "NVDA",
    "weight": 4.8,
    "limit": 5.0,
    "status": "warning",
    "marketValue": 2400000,
    "asOfDate": "2025-01-15",
    "createdAt": "2025-01-15T08:00:00Z",
    "updatedAt": "2025-01-15T08:00:00Z"
  },
  {
    "id": "conc-004",
    "portfolioId": "pf-001",
    "type": "singlePosition",
    "name": "Amazon.com Inc (AMZN)",
    "identifier": "AMZN",
    "weight": 4.2,
    "limit": 5.0,
    "status": "ok",
    "marketValue": 2100000,
    "asOfDate": "2025-01-15",
    "createdAt": "2025-01-15T08:00:00Z",
    "updatedAt": "2025-01-15T08:00:00Z"
  },
  {
    "id": "conc-005",
    "portfolioId": "pf-001",
    "type": "singlePosition",
    "name": "Alphabet Inc (GOOGL)",
    "identifier": "GOOGL",
    "weight": 3.8,
    "limit": 5.0,
    "status": "ok",
    "marketValue": 1900000,
    "asOfDate": "2025-01-15",
    "createdAt": "2025-01-15T08:00:00Z",
    "updatedAt": "2025-01-15T08:00:00Z"
  },
  {
    "id": "conc-006",
    "portfolioId": "pf-001",
    "type": "issuer",
    "name": "US Treasury",
    "identifier": "UST",
    "weight": 12.5,
    "limit": 15.0,
    "status": "ok",
    "marketValue": 6250000,
    "asOfDate": "2025-01-15",
    "createdAt": "2025-01-15T08:00:00Z",
    "updatedAt": "2025-01-15T08:00:00Z"
  },
  {
    "id": "conc-007",
    "portfolioId": "pf-001",
    "type": "issuer",
    "name": "JPMorgan Chase & Co",
    "identifier": "JPM",
    "weight": 5.8,
    "limit": 5.0,
    "status": "breached",
    "marketValue": 2900000,
    "asOfDate": "2025-01-15",
    "createdAt": "2025-01-15T08:00:00Z",
    "updatedAt": "2025-01-15T08:00:00Z"
  },
  {
    "id": "conc-008",
    "portfolioId": "pf-001",
    "type": "issuer",
    "name": "Berkshire Hathaway",
    "identifier": "BRK",
    "weight": 4.5,
    "limit": 5.0,
    "status": "warning",
    "marketValue": 2250000,
    "asOfDate": "2025-01-15",
    "createdAt": "2025-01-15T08:00:00Z",
    "updatedAt": "2025-01-15T08:00:00Z"
  },
  {
    "id": "conc-009",
    "portfolioId": "pf-001",
    "type": "sector",
    "name": "Technology Sector",
    "identifier": "TECH",
    "weight": 24.5,
    "limit": 25.0,
    "status": "warning",
    "marketValue": 12250000,
    "asOfDate": "2025-01-15",
    "createdAt": "2025-01-15T08:00:00Z",
    "updatedAt": "2025-01-15T08:00:00Z"
  },
  {
    "id": "conc-010",
    "portfolioId": "pf-001",
    "type": "sector",
    "name": "Financial Sector",
    "identifier": "FIN",
    "weight": 14.2,
    "limit": 20.0,
    "status": "ok",
    "marketValue": 7100000,
    "asOfDate": "2025-01-15",
    "createdAt": "2025-01-15T08:00:00Z",
    "updatedAt": "2025-01-15T08:00:00Z"
  },
  {
    "id": "conc-011",
    "portfolioId": "pf-001",
    "type": "country",
    "name": "United States",
    "identifier": "USA",
    "weight": 52.3,
    "limit": 60.0,
    "status": "ok",
    "marketValue": 26150000,
    "asOfDate": "2025-01-15",
    "createdAt": "2025-01-15T08:00:00Z",
    "updatedAt": "2025-01-15T08:00:00Z"
  },
  {
    "id": "conc-012",
    "portfolioId": "pf-001",
    "type": "country",
    "name": "China",
    "identifier": "CHN",
    "weight": 8.2,
    "limit": 10.0,
    "status": "ok",
    "marketValue": 4100000,
    "asOfDate": "2025-01-15",
    "createdAt": "2025-01-15T08:00:00Z",
    "updatedAt": "2025-01-15T08:00:00Z"
  },
  {
    "id": "conc-013",
    "portfolioId": "pf-001",
    "type": "country",
    "name": "United Kingdom",
    "identifier": "GBR",
    "weight": 6.5,
    "limit": 10.0,
    "status": "ok",
    "marketValue": 3250000,
    "asOfDate": "2025-01-15",
    "createdAt": "2025-01-15T08:00:00Z",
    "updatedAt": "2025-01-15T08:00:00Z"
  },
  {
    "id": "conc-014",
    "portfolioId": "pf-002",
    "type": "singlePosition",
    "name": "Johnson & Johnson (JNJ)",
    "identifier": "JNJ",
    "weight": 6.2,
    "limit": 5.0,
    "status": "breached",
    "marketValue": 1240000,
    "asOfDate": "2025-01-15",
    "createdAt": "2025-01-15T08:00:00Z",
    "updatedAt": "2025-01-15T08:00:00Z"
  },
  {
    "id": "conc-015",
    "portfolioId": "pf-002",
    "type": "singlePosition",
    "name": "UnitedHealth Group (UNH)",
    "identifier": "UNH",
    "weight": 4.8,
    "limit": 5.0,
    "status": "warning",
    "marketValue": 960000,
    "asOfDate": "2025-01-15",
    "createdAt": "2025-01-15T08:00:00Z",
    "updatedAt": "2025-01-15T08:00:00Z"
  },
  {
    "id": "conc-016",
    "portfolioId": "pf-002",
    "type": "sector",
    "name": "Healthcare Sector",
    "identifier": "HLTH",
    "weight": 15.0,
    "limit": 15.0,
    "status": "warning",
    "marketValue": 3000000,
    "asOfDate": "2025-01-15",
    "createdAt": "2025-01-15T08:00:00Z",
    "updatedAt": "2025-01-15T08:00:00Z"
  },
  {
    "id": "conc-017",
    "portfolioId": "pf-002",
    "type": "country",
    "name": "Germany",
    "identifier": "DEU",
    "weight": 12.0,
    "limit": 10.0,
    "status": "breached",
    "marketValue": 2400000,
    "asOfDate": "2025-01-15",
    "createdAt": "2025-01-15T08:00:00Z",
    "updatedAt": "2025-01-15T08:00:00Z"
  },
  {
    "id": "conc-018",
    "portfolioId": "pf-002",
    "type": "issuer",
    "name": "German Bunds",
    "identifier": "BUND",
    "weight": 8.5,
    "limit": 10.0,
    "status": "ok",
    "marketValue": 1700000,
    "asOfDate": "2025-01-15",
    "createdAt": "2025-01-15T08:00:00Z",
    "updatedAt": "2025-01-15T08:00:00Z"
  },
  {
    "id": "conc-019",
    "portfolioId": "pf-003",
    "type": "singlePosition",
    "name": "Tesla Inc (TSLA)",
    "identifier": "TSLA",
    "weight": 9.2,
    "limit": 5.0,
    "status": "breached",
    "marketValue": 4600000,
    "asOfDate": "2025-01-15",
    "createdAt": "2025-01-15T08:00:00Z",
    "updatedAt": "2025-01-15T08:00:00Z"
  },
  {
    "id": "conc-020",
    "portfolioId": "pf-003",
    "type": "singlePosition",
    "name": "Meta Platforms (META)",
    "identifier": "META",
    "weight": 6.5,
    "limit": 5.0,
    "status": "breached",
    "marketValue": 3250000,
    "asOfDate": "2025-01-15",
    "createdAt": "2025-01-15T08:00:00Z",
    "updatedAt": "2025-01-15T08:00:00Z"
  },
  {
    "id": "conc-021",
    "portfolioId": "pf-003",
    "type": "sector",
    "name": "Technology Sector",
    "identifier": "TECH",
    "weight": 32.0,
    "limit": 25.0,
    "status": "breached",
    "marketValue": 16000000,
    "asOfDate": "2025-01-15",
    "createdAt": "2025-01-15T08:00:00Z",
    "updatedAt": "2025-01-15T08:00:00Z"
  },
  {
    "id": "conc-022",
    "portfolioId": "pf-003",
    "type": "country",
    "name": "United States",
    "identifier": "USA",
    "weight": 60.0,
    "limit": 55.0,
    "status": "breached",
    "marketValue": 30000000,
    "asOfDate": "2025-01-15",
    "createdAt": "2025-01-15T08:00:00Z",
    "updatedAt": "2025-01-15T08:00:00Z"
  },
  {
    "id": "conc-023",
    "portfolioId": "pf-001",
    "type": "currency",
    "name": "USD Currency Exposure",
    "identifier": "USD",
    "weight": 55.0,
    "limit": 60.0,
    "status": "ok",
    "marketValue": 27500000,
    "asOfDate": "2025-01-15",
    "createdAt": "2025-01-15T08:00:00Z",
    "updatedAt": "2025-01-15T08:00:00Z"
  },
  {
    "id": "conc-024",
    "portfolioId": "pf-001",
    "type": "counterparty",
    "name": "Goldman Sachs (Prime Broker)",
    "identifier": "GS-PB",
    "weight": 18.0,
    "limit": 20.0,
    "status": "warning",
    "marketValue": 9000000,
    "asOfDate": "2025-01-15",
    "createdAt": "2025-01-15T08:00:00Z",
    "updatedAt": "2025-01-15T08:00:00Z"
  },
  {
    "id": "conc-025",
    "portfolioId": "pf-001",
    "type": "counterparty",
    "name": "Morgan Stanley (Prime Broker)",
    "identifier": "MS-PB",
    "weight": 15.0,
    "limit": 20.0,
    "status": "ok",
    "marketValue": 7500000,
    "asOfDate": "2025-01-15",
    "createdAt": "2025-01-15T08:00:00Z",
    "updatedAt": "2025-01-15T08:00:00Z"
  },
  {
    "id": "conc-026",
    "portfolioId": "pf-002",
    "type": "currency",
    "name": "EUR Currency Exposure",
    "identifier": "EUR",
    "weight": 25.0,
    "limit": 25.0,
    "status": "warning",
    "marketValue": 5000000,
    "asOfDate": "2025-01-15",
    "createdAt": "2025-01-15T08:00:00Z",
    "updatedAt": "2025-01-15T08:00:00Z"
  },
  {
    "id": "conc-027",
    "portfolioId": "pf-003",
    "type": "liquidity",
    "name": "Illiquid Investments",
    "identifier": "ILLIQ",
    "weight": 2.0,
    "limit": 5.0,
    "status": "ok",
    "marketValue": 1000000,
    "asOfDate": "2025-01-15",
    "createdAt": "2025-01-15T08:00:00Z",
    "updatedAt": "2025-01-15T08:00:00Z"
  },
  {
    "id": "conc-028",
    "portfolioId": "pf-001",
    "type": "maturity",
    "name": "Short-term Debt (<1 year)",
    "identifier": "ST-DEBT",
    "weight": 8.0,
    "limit": 10.0,
    "status": "ok",
    "marketValue": 4000000,
    "asOfDate": "2025-01-15",
    "createdAt": "2025-01-15T08:00:00Z",
    "updatedAt": "2025-01-15T08:00:00Z"
  },
  {
    "id": "conc-029",
    "portfolioId": "pf-001",
    "type": "creditRating",
    "name": "High Yield (BB and below)",
    "identifier": "HY",
    "weight": 12.0,
    "limit": 15.0,
    "status": "ok",
    "marketValue": 6000000,
    "asOfDate": "2025-01-15",
    "createdAt": "2025-01-15T08:00:00Z",
    "updatedAt": "2025-01-15T08:00:00Z"
  },
  {
    "id": "conc-030",
    "portfolioId": "pf-002",
    "type": "strategy",
    "name": "Momentum Strategy",
    "identifier": "MOMENTUM",
    "weight": 22.0,
    "limit": 20.0,
    "status": "breached",
    "marketValue": 4400000,
    "asOfDate": "2025-01-15",
    "createdAt": "2025-01-15T08:00:00Z",
    "updatedAt": "2025-01-15T08:00:00Z"
  }
]
