{
  "kbTags": [
    {"id":"tag-001","clientId":"client-1","tagKey":"onboarding","labelRu":"Онбординг","labelEn":"Onboarding","labelUk":"Онбординг","colorKey":"emerald","usageCount":12,"createdAt":"2024-01-01T00:00:00Z"},
    {"id":"tag-002","clientId":"client-1","tagKey":"security","labelRu":"Безопасность","labelEn":"Security","labelUk":"Безпека","colorKey":"rose","usageCount":8,"createdAt":"2024-01-01T00:00:00Z"},
    {"id":"tag-003","clientId":"client-1","tagKey":"compliance","labelRu":"Комплаенс","labelEn":"Compliance","labelUk":"Комплаєнс","colorKey":"amber","usageCount":10,"createdAt":"2024-01-01T00:00:00Z"},
    {"id":"tag-004","clientId":"client-1","tagKey":"reporting","labelRu":"Отчетность","labelEn":"Reporting","labelUk":"Звітність","colorKey":"blue","usageCount":15,"createdAt":"2024-01-01T00:00:00Z"},
    {"id":"tag-005","clientId":"client-1","tagKey":"documents","labelRu":"Документы","labelEn":"Documents","labelUk":"Документи","colorKey":"purple","usageCount":9,"createdAt":"2024-01-01T00:00:00Z"},
    {"id":"tag-006","clientId":"client-1","tagKey":"ips","labelRu":"IPS","labelEn":"IPS","labelUk":"IPS","colorKey":"emerald","usageCount":6,"createdAt":"2024-01-01T00:00:00Z"},
    {"id":"tag-007","clientId":"client-1","tagKey":"tax","labelRu":"Налоги","labelEn":"Tax","labelUk":"Податки","colorKey":"amber","usageCount":7,"createdAt":"2024-01-01T00:00:00Z"},
    {"id":"tag-008","clientId":"client-1","tagKey":"trust","labelRu":"Трасты","labelEn":"Trust","labelUk":"Трасти","colorKey":"purple","usageCount":5,"createdAt":"2024-01-01T00:00:00Z"},
    {"id":"tag-009","clientId":"client-1","tagKey":"workflow","labelRu":"Workflow","labelEn":"Workflow","labelUk":"Workflow","colorKey":"blue","usageCount":11,"createdAt":"2024-01-01T00:00:00Z"},
    {"id":"tag-010","clientId":"client-1","tagKey":"risk","labelRu":"Риски","labelEn":"Risk","labelUk":"Ризики","colorKey":"rose","usageCount":8,"createdAt":"2024-01-01T00:00:00Z"},
    {"id":"tag-011","clientId":"client-1","tagKey":"integration","labelRu":"Интеграции","labelEn":"Integrations","labelUk":"Інтеграції","colorKey":"stone","usageCount":4,"createdAt":"2024-01-01T00:00:00Z"},
    {"id":"tag-012","clientId":"client-1","tagKey":"billing","labelRu":"Биллинг","labelEn":"Billing","labelUk":"Білінг","colorKey":"emerald","usageCount":6,"createdAt":"2024-01-01T00:00:00Z"},
    {"id":"tag-013","clientId":"client-1","tagKey":"client-portal","labelRu":"Портал клиента","labelEn":"Client Portal","labelUk":"Портал клієнта","colorKey":"blue","usageCount":7,"createdAt":"2024-01-01T00:00:00Z"},
    {"id":"tag-014","clientId":"client-1","tagKey":"mobile","labelRu":"Мобильный","labelEn":"Mobile","labelUk":"Мобільний","colorKey":"purple","usageCount":3,"createdAt":"2024-01-01T00:00:00Z"},
    {"id":"tag-015","clientId":"client-1","tagKey":"api","labelRu":"API","labelEn":"API","labelUk":"API","colorKey":"stone","usageCount":4,"createdAt":"2024-01-01T00:00:00Z"},
    {"id":"tag-016","clientId":"client-1","tagKey":"performance","labelRu":"Эффективность","labelEn":"Performance","labelUk":"Ефективність","colorKey":"emerald","usageCount":5,"createdAt":"2024-01-01T00:00:00Z"},
    {"id":"tag-017","clientId":"client-1","tagKey":"reconciliation","labelRu":"Сверка","labelEn":"Reconciliation","labelUk":"Звірка","colorKey":"amber","usageCount":4,"createdAt":"2024-01-01T00:00:00Z"},
    {"id":"tag-018","clientId":"client-1","tagKey":"sop","labelRu":"SOP","labelEn":"SOP","labelUk":"SOP","colorKey":"rose","usageCount":12,"createdAt":"2024-01-01T00:00:00Z"},
    {"id":"tag-019","clientId":"client-1","tagKey":"best-practice","labelRu":"Best Practice","labelEn":"Best Practice","labelUk":"Best Practice","colorKey":"emerald","usageCount":9,"createdAt":"2024-01-01T00:00:00Z"},
    {"id":"tag-020","clientId":"client-1","tagKey":"faq","labelRu":"FAQ","labelEn":"FAQ","labelUk":"FAQ","colorKey":"blue","usageCount":15,"createdAt":"2024-01-01T00:00:00Z"},
    {"id":"tag-021","clientId":"client-1","tagKey":"privacy","labelRu":"Приватность","labelEn":"Privacy","labelUk":"Приватність","colorKey":"rose","usageCount":3,"createdAt":"2024-01-01T00:00:00Z"},
    {"id":"tag-022","clientId":"client-1","tagKey":"data","labelRu":"Данные","labelEn":"Data","labelUk":"Дані","colorKey":"purple","usageCount":6,"createdAt":"2024-01-01T00:00:00Z"},
    {"id":"tag-023","clientId":"client-1","tagKey":"kyc","labelRu":"KYC","labelEn":"KYC","labelUk":"KYC","colorKey":"amber","usageCount":5,"createdAt":"2024-01-01T00:00:00Z"},
    {"id":"tag-024","clientId":"client-1","tagKey":"aml","labelRu":"AML","labelEn":"AML","labelUk":"AML","colorKey":"rose","usageCount":4,"createdAt":"2024-01-01T00:00:00Z"},
    {"id":"tag-025","clientId":"client-1","tagKey":"estate","labelRu":"Estate","labelEn":"Estate","labelUk":"Estate","colorKey":"purple","usageCount":3,"createdAt":"2024-01-01T00:00:00Z"},
    {"id":"tag-026","clientId":"client-1","tagKey":"investment","labelRu":"Инвестиции","labelEn":"Investment","labelUk":"Інвестиції","colorKey":"emerald","usageCount":8,"createdAt":"2024-01-01T00:00:00Z"},
    {"id":"tag-027","clientId":"client-1","tagKey":"portfolio","labelRu":"Портфель","labelEn":"Portfolio","labelUk":"Портфель","colorKey":"blue","usageCount":7,"createdAt":"2024-01-01T00:00:00Z"},
    {"id":"tag-028","clientId":"client-1","tagKey":"custodian","labelRu":"Кастодиан","labelEn":"Custodian","labelUk":"Кастодіан","colorKey":"stone","usageCount":4,"createdAt":"2024-01-01T00:00:00Z"},
    {"id":"tag-029","clientId":"client-1","tagKey":"admin","labelRu":"Администрирование","labelEn":"Admin","labelUk":"Адміністрування","colorKey":"amber","usageCount":6,"createdAt":"2024-01-01T00:00:00Z"},
    {"id":"tag-030","clientId":"client-1","tagKey":"automation","labelRu":"Автоматизация","labelEn":"Automation","labelUk":"Автоматизація","colorKey":"purple","usageCount":5,"createdAt":"2024-01-01T00:00:00Z"},
    {"id":"tag-031","clientId":"client-1","tagKey":"alerts","labelRu":"Алерты","labelEn":"Alerts","labelUk":"Алерти","colorKey":"rose","usageCount":4,"createdAt":"2024-01-01T00:00:00Z"},
    {"id":"tag-032","clientId":"client-1","tagKey":"dashboard","labelRu":"Дашборд","labelEn":"Dashboard","labelUk":"Дашборд","colorKey":"emerald","usageCount":6,"createdAt":"2024-01-01T00:00:00Z"},
    {"id":"tag-033","clientId":"client-1","tagKey":"fees","labelRu":"Комиссии","labelEn":"Fees","labelUk":"Комісії","colorKey":"amber","usageCount":5,"createdAt":"2024-01-01T00:00:00Z"},
    {"id":"tag-034","clientId":"client-1","tagKey":"approval","labelRu":"Согласование","labelEn":"Approval","labelUk":"Погодження","colorKey":"blue","usageCount":7,"createdAt":"2024-01-01T00:00:00Z"},
    {"id":"tag-035","clientId":"client-1","tagKey":"notification","labelRu":"Уведомления","labelEn":"Notifications","labelUk":"Сповіщення","colorKey":"purple","usageCount":4,"createdAt":"2024-01-01T00:00:00Z"},
    {"id":"tag-036","clientId":"client-1","tagKey":"export","labelRu":"Экспорт","labelEn":"Export","labelUk":"Експорт","colorKey":"stone","usageCount":3,"createdAt":"2024-01-01T00:00:00Z"},
    {"id":"tag-037","clientId":"client-1","tagKey":"import","labelRu":"Импорт","labelEn":"Import","labelUk":"Імпорт","colorKey":"stone","usageCount":3,"createdAt":"2024-01-01T00:00:00Z"},
    {"id":"tag-038","clientId":"client-1","tagKey":"ai","labelRu":"AI","labelEn":"AI","labelUk":"AI","colorKey":"purple","usageCount":4,"createdAt":"2024-01-01T00:00:00Z"},
    {"id":"tag-039","clientId":"client-1","tagKey":"copilot","labelRu":"Copilot","labelEn":"Copilot","labelUk":"Copilot","colorKey":"emerald","usageCount":3,"createdAt":"2024-01-01T00:00:00Z"},
    {"id":"tag-040","clientId":"client-1","tagKey":"guide","labelRu":"Гайд","labelEn":"Guide","labelUk":"Гайд","colorKey":"blue","usageCount":10,"createdAt":"2024-01-01T00:00:00Z"}
  ],
  "kbArticles": [
    {"id":"art-001","clientId":"client-1","titleRu":"Начало работы с Wealth OS","titleEn":"Getting Started with Wealth OS","bodyRu":"# Начало работы\n\nДобро пожаловать в Wealth OS...","bodyEn":"# Getting Started\n\nWelcome to Wealth OS...","tagsJson":["onboarding","guide"],"audience":"both","status":"published","relatedModuleKeysJson":["dashboard-home"],"authorId":"user-1","viewCount":156,"createdAt":"2024-06-01T00:00:00Z","updatedAt":"2025-01-10T00:00:00Z"},
    {"id":"art-002","clientId":"client-1","titleRu":"Настройка двухфакторной аутентификации","titleEn":"Setting Up Two-Factor Authentication","bodyRu":"# Двухфакторная аутентификация\n\nДля безопасности...","bodyEn":"# Two-Factor Authentication\n\nFor security...","tagsJson":["security","sop"],"audience":"both","status":"published","relatedModuleKeysJson":["security"],"authorId":"user-1","viewCount":89,"createdAt":"2024-06-05T00:00:00Z","updatedAt":"2025-01-08T00:00:00Z"},
    {"id":"art-003","clientId":"client-1","titleRu":"Загрузка документов в хранилище","titleEn":"Uploading Documents to Vault","bodyRu":"# Документы\n\nКак загружать документы...","bodyEn":"# Documents\n\nHow to upload documents...","tagsJson":["documents","guide"],"audience":"both","status":"published","relatedModuleKeysJson":["documents"],"authorId":"user-2","viewCount":234,"createdAt":"2024-06-10T00:00:00Z","updatedAt":"2025-01-05T00:00:00Z"},
    {"id":"art-004","clientId":"client-1","titleRu":"SOP: Ежедневная сверка позиций","titleEn":"SOP: Daily Position Reconciliation","bodyRu":"# Ежедневная сверка\n\n## Цель\nОбеспечить точность...","bodyEn":"# Daily Reconciliation\n\n## Purpose\nEnsure accuracy...","tagsJson":["reconciliation","sop"],"audience":"staff","status":"published","relatedModuleKeysJson":["reconciliation"],"authorId":"user-1","viewCount":67,"createdAt":"2024-07-01T00:00:00Z","updatedAt":"2025-01-12T00:00:00Z"},
    {"id":"art-005","clientId":"client-1","titleRu":"Понимание IPS: Руководство для клиентов","titleEn":"Understanding IPS: Client Guide","bodyRu":"# Investment Policy Statement\n\nIPS определяет...","bodyEn":"# Investment Policy Statement\n\nIPS defines...","tagsJson":["ips","client-portal"],"audience":"client","status":"published","relatedModuleKeysJson":["ips"],"authorId":"user-2","viewCount":45,"createdAt":"2024-07-15T00:00:00Z","updatedAt":"2024-12-20T00:00:00Z"},
    {"id":"art-006","clientId":"client-1","titleRu":"Налоговая отчетность: Обзор","titleEn":"Tax Reporting Overview","bodyRu":"# Налоговая отчетность\n\n> ⚠️ Данный материал носит информационный характер...","bodyEn":"# Tax Reporting\n\n> ⚠️ This material is for informational purposes...","tagsJson":["tax","reporting"],"audience":"both","status":"published","relatedModuleKeysJson":["tax"],"authorId":"user-1","viewCount":78,"createdAt":"2024-08-01T00:00:00Z","updatedAt":"2025-01-03T00:00:00Z"},
    {"id":"art-007","clientId":"client-1","titleRu":"Работа с трастами","titleEn":"Working with Trusts","bodyRu":"# Трасты\n\n> ⚠️ Не является юридической консультацией...","bodyEn":"# Trusts\n\n> ⚠️ Not legal advice...","tagsJson":["trust","estate"],"audience":"both","status":"published","relatedModuleKeysJson":["trust-estate"],"authorId":"user-2","viewCount":56,"createdAt":"2024-08-15T00:00:00Z","updatedAt":"2024-12-15T00:00:00Z"},
    {"id":"art-008","clientId":"client-1","titleRu":"SOP: Обработка KYC документов","titleEn":"SOP: KYC Document Processing","bodyRu":"# KYC Процесс\n\n## Шаги\n1. Получить документы...","bodyEn":"# KYC Process\n\n## Steps\n1. Receive documents...","tagsJson":["kyc","compliance","sop"],"audience":"staff","status":"published","relatedModuleKeysJson":["onboarding"],"authorId":"user-1","viewCount":89,"createdAt":"2024-09-01T00:00:00Z","updatedAt":"2025-01-10T00:00:00Z"},
    {"id":"art-009","clientId":"client-1","titleRu":"Настройка уведомлений","titleEn":"Notification Settings","bodyRu":"# Уведомления\n\nКак настроить...","bodyEn":"# Notifications\n\nHow to configure...","tagsJson":["notification","guide"],"audience":"both","status":"published","relatedModuleKeysJson":["mobile"],"authorId":"user-2","viewCount":112,"createdAt":"2024-09-15T00:00:00Z","updatedAt":"2025-01-08T00:00:00Z"},
    {"id":"art-010","clientId":"client-1","titleRu":"Управление рисками портфеля","titleEn":"Portfolio Risk Management","bodyRu":"# Риски портфеля\n\nОсновные метрики...","bodyEn":"# Portfolio Risks\n\nKey metrics...","tagsJson":["risk","portfolio"],"audience":"staff","status":"published","relatedModuleKeysJson":["risk"],"authorId":"user-1","viewCount":67,"createdAt":"2024-10-01T00:00:00Z","updatedAt":"2025-01-05T00:00:00Z"},
    {"id":"art-011","clientId":"client-1","titleRu":"Интеграция с кастодианами","titleEn":"Custodian Integration","bodyRu":"# Интеграции\n\nПоддерживаемые кастодианы...","bodyEn":"# Integrations\n\nSupported custodians...","tagsJson":["integration","custodian"],"audience":"staff","status":"published","relatedModuleKeysJson":["integrations"],"authorId":"user-1","viewCount":45,"createdAt":"2024-10-15T00:00:00Z","updatedAt":"2024-12-20T00:00:00Z"},
    {"id":"art-012","clientId":"client-1","titleRu":"Использование AI Copilot","titleEn":"Using AI Copilot","bodyRu":"# AI Copilot\n\nAI помощник позволяет...","bodyEn":"# AI Copilot\n\nAI assistant allows...","tagsJson":["ai","copilot"],"audience":"both","status":"published","relatedModuleKeysJson":["ai"],"authorId":"user-2","viewCount":178,"createdAt":"2024-11-01T00:00:00Z","updatedAt":"2025-01-12T00:00:00Z"},
    {"id":"art-013","clientId":"client-1","titleRu":"Генерация отчетов","titleEn":"Report Generation","bodyRu":"# Отчеты\n\nКак создавать отчеты...","bodyEn":"# Reports\n\nHow to generate reports...","tagsJson":["reporting","export"],"audience":"both","status":"published","relatedModuleKeysJson":["reporting"],"authorId":"user-1","viewCount":134,"createdAt":"2024-11-15T00:00:00Z","updatedAt":"2025-01-08T00:00:00Z"},
    {"id":"art-014","clientId":"client-1","titleRu":"Согласование платежей","titleEn":"Payment Approvals","bodyRu":"# Согласования\n\nПроцесс согласования...","bodyEn":"# Approvals\n\nApproval process...","tagsJson":["approval","workflow"],"audience":"staff","status":"published","relatedModuleKeysJson":["billpay-checks"],"authorId":"user-2","viewCount":89,"createdAt":"2024-12-01T00:00:00Z","updatedAt":"2025-01-10T00:00:00Z"},
    {"id":"art-015","clientId":"client-1","titleRu":"Мониторинг AML алертов","titleEn":"AML Alert Monitoring","bodyRu":"# AML Мониторинг\n\nПроцедура обработки...","bodyEn":"# AML Monitoring\n\nProcessing procedure...","tagsJson":["aml","compliance","alerts"],"audience":"staff","status":"published","relatedModuleKeysJson":["onboarding"],"authorId":"user-1","viewCount":56,"createdAt":"2024-12-15T00:00:00Z","updatedAt":"2025-01-05T00:00:00Z"},
    {"id":"art-016","clientId":"client-1","titleRu":"Черновик: Новые функции Q1","titleEn":"Draft: Q1 New Features","bodyRu":"# Новые функции\n\nВ разработке...","bodyEn":"# New Features\n\nIn development...","tagsJson":["guide"],"audience":"staff","status":"draft","relatedModuleKeysJson":[],"authorId":"user-1","viewCount":12,"createdAt":"2025-01-01T00:00:00Z","updatedAt":"2025-01-15T00:00:00Z"},
    {"id":"art-017","clientId":"client-1","titleRu":"Работа с дашбордом","titleEn":"Working with Dashboard","bodyRu":"# Дашборд\n\nОбзор главного экрана...","bodyEn":"# Dashboard\n\nMain screen overview...","tagsJson":["dashboard","guide"],"audience":"both","status":"published","relatedModuleKeysJson":["dashboard-home"],"authorId":"user-2","viewCount":201,"createdAt":"2024-06-20T00:00:00Z","updatedAt":"2025-01-10T00:00:00Z"},
    {"id":"art-018","clientId":"client-1","titleRu":"Настройка комиссий","titleEn":"Fee Configuration","bodyRu":"# Комиссии\n\nКак настроить структуру...","bodyEn":"# Fees\n\nHow to configure structure...","tagsJson":["fees","billing"],"audience":"staff","status":"published","relatedModuleKeysJson":["fee-billing"],"authorId":"user-1","viewCount":45,"createdAt":"2024-07-20T00:00:00Z","updatedAt":"2024-12-20T00:00:00Z"},
    {"id":"art-019","clientId":"client-1","titleRu":"API для разработчиков","titleEn":"API for Developers","bodyRu":"# API\n\nДокументация по API...","bodyEn":"# API\n\nAPI documentation...","tagsJson":["api","integration"],"audience":"staff","status":"published","relatedModuleKeysJson":["api"],"authorId":"user-1","viewCount":34,"createdAt":"2024-08-20T00:00:00Z","updatedAt":"2024-12-15T00:00:00Z"},
    {"id":"art-020","clientId":"client-1","titleRu":"Best Practices: Безопасность данных","titleEn":"Best Practices: Data Security","bodyRu":"# Безопасность данных\n\nРекомендации...","bodyEn":"# Data Security\n\nRecommendations...","tagsJson":["security","data","best-practice"],"audience":"staff","status":"published","relatedModuleKeysJson":["security"],"authorId":"user-2","viewCount":78,"createdAt":"2024-09-20T00:00:00Z","updatedAt":"2025-01-08T00:00:00Z"}
  ],
  "kbCourses": [
    {"id":"crs-001","clientId":"client-1","titleRu":"Онбординг нового сотрудника MFO","titleEn":"New MFO Employee Onboarding","descriptionRu":"Полный курс для новых сотрудников","audience":"staff","lessonIdsJson":["les-001","les-002","les-003","les-004","les-005"],"status":"active","estimatedDurationMin":120,"relatedChecklistId":"chk-001","createdAt":"2024-06-01T00:00:00Z","updatedAt":"2025-01-10T00:00:00Z"},
    {"id":"crs-002","clientId":"client-1","titleRu":"Основы работы с платформой для клиентов","titleEn":"Platform Basics for Clients","descriptionRu":"Введение в использование портала","audience":"client","lessonIdsJson":["les-006","les-007","les-008"],"status":"active","estimatedDurationMin":45,"createdAt":"2024-07-01T00:00:00Z","updatedAt":"2025-01-05T00:00:00Z"},
    {"id":"crs-003","clientId":"client-1","titleRu":"Compliance и KYC процессы","titleEn":"Compliance and KYC Processes","descriptionRu":"Детальный курс по комплаенс","audience":"staff","lessonIdsJson":["les-009","les-010","les-011","les-012"],"status":"active","estimatedDurationMin":90,"relatedChecklistId":"chk-002","createdAt":"2024-08-01T00:00:00Z","updatedAt":"2025-01-08T00:00:00Z"},
    {"id":"crs-004","clientId":"client-1","titleRu":"Работа с документами","titleEn":"Document Management","descriptionRu":"Управление документами в системе","audience":"both","lessonIdsJson":["les-013","les-014","les-015"],"status":"active","estimatedDurationMin":60,"createdAt":"2024-09-01T00:00:00Z","updatedAt":"2025-01-03T00:00:00Z"},
    {"id":"crs-005","clientId":"client-1","titleRu":"Безопасность и приватность","titleEn":"Security and Privacy","descriptionRu":"Основы информационной безопасности","audience":"both","lessonIdsJson":["les-016","les-017","les-018"],"status":"active","estimatedDurationMin":50,"relatedChecklistId":"chk-003","createdAt":"2024-10-01T00:00:00Z","updatedAt":"2025-01-10T00:00:00Z"},
    {"id":"crs-006","clientId":"client-1","titleRu":"Отчетность и аналитика","titleEn":"Reporting and Analytics","descriptionRu":"Создание и анализ отчетов","audience":"staff","lessonIdsJson":["les-019","les-020","les-021","les-022"],"status":"active","estimatedDurationMin":80,"createdAt":"2024-11-01T00:00:00Z","updatedAt":"2025-01-05T00:00:00Z"},
    {"id":"crs-007","clientId":"client-1","titleRu":"IPS и ограничения","titleEn":"IPS and Constraints","descriptionRu":"Работа с инвестиционными политиками","audience":"staff","lessonIdsJson":["les-023","les-024","les-025"],"status":"active","estimatedDurationMin":70,"createdAt":"2024-12-01T00:00:00Z","updatedAt":"2025-01-08T00:00:00Z"},
    {"id":"crs-008","clientId":"client-1","titleRu":"Налоговое планирование","titleEn":"Tax Planning","descriptionRu":"Основы налогового учета","audience":"staff","lessonIdsJson":["les-026","les-027","les-028"],"status":"active","estimatedDurationMin":75,"createdAt":"2024-12-15T00:00:00Z","updatedAt":"2025-01-10T00:00:00Z"},
    {"id":"crs-009","clientId":"client-1","titleRu":"Трасты и Estate Planning","titleEn":"Trusts and Estate Planning","descriptionRu":"Работа с трастами","audience":"staff","lessonIdsJson":["les-029","les-030"],"status":"active","estimatedDurationMin":60,"createdAt":"2025-01-01T00:00:00Z","updatedAt":"2025-01-12T00:00:00Z"},
    {"id":"crs-010","clientId":"client-1","titleRu":"AI Copilot: Продвинутое использование","titleEn":"AI Copilot: Advanced Usage","descriptionRu":"Максимум от AI помощника","audience":"staff","lessonIdsJson":["les-031","les-032"],"status":"active","estimatedDurationMin":40,"createdAt":"2025-01-05T00:00:00Z","updatedAt":"2025-01-15T00:00:00Z"},
    {"id":"crs-011","clientId":"client-1","titleRu":"Управление рисками","titleEn":"Risk Management","descriptionRu":"Анализ и контроль рисков","audience":"staff","lessonIdsJson":["les-033","les-034","les-035"],"status":"active","estimatedDurationMin":65,"createdAt":"2024-11-15T00:00:00Z","updatedAt":"2025-01-08T00:00:00Z"},
    {"id":"crs-012","clientId":"client-1","titleRu":"Черновик: Новый курс","titleEn":"Draft: New Course","descriptionRu":"В разработке","audience":"staff","lessonIdsJson":[],"status":"draft","estimatedDurationMin":0,"createdAt":"2025-01-10T00:00:00Z","updatedAt":"2025-01-15T00:00:00Z"}
  ],
  "kbLessons": [
    {"id":"les-001","clientId":"client-1","courseId":"crs-001","titleRu":"Введение в Wealth OS","titleEn":"Introduction to Wealth OS","bodyRu":"# Добро пожаловать\n\nВ этом уроке вы узнаете...","durationMin":20,"audience":"staff","orderIndex":1,"createdAt":"2024-06-01T00:00:00Z","updatedAt":"2025-01-10T00:00:00Z"},
    {"id":"les-002","clientId":"client-1","courseId":"crs-001","titleRu":"Навигация по системе","titleEn":"System Navigation","bodyRu":"# Навигация\n\nОсновные разделы...","durationMin":25,"audience":"staff","orderIndex":2,"createdAt":"2024-06-01T00:00:00Z","updatedAt":"2025-01-10T00:00:00Z"},
    {"id":"les-003","clientId":"client-1","courseId":"crs-001","titleRu":"Работа с клиентами","titleEn":"Working with Clients","bodyRu":"# Клиенты\n\nКак управлять...","durationMin":30,"audience":"staff","orderIndex":3,"createdAt":"2024-06-01T00:00:00Z","updatedAt":"2025-01-10T00:00:00Z"},
    {"id":"les-004","clientId":"client-1","courseId":"crs-001","titleRu":"Задачи и workflow","titleEn":"Tasks and Workflow","bodyRu":"# Workflow\n\nПроцессы согласования...","durationMin":25,"audience":"staff","orderIndex":4,"createdAt":"2024-06-01T00:00:00Z","updatedAt":"2025-01-10T00:00:00Z"},
    {"id":"les-005","clientId":"client-1","courseId":"crs-001","titleRu":"Завершение онбординга","titleEn":"Completing Onboarding","bodyRu":"# Финал\n\nПоздравляем...","durationMin":20,"quizJson":{"questions":[{"q":"Где найти список задач?","options":["Dashboard","Documents","Settings"],"correct":0}]},"audience":"staff","orderIndex":5,"createdAt":"2024-06-01T00:00:00Z","updatedAt":"2025-01-10T00:00:00Z"},
    {"id":"les-006","clientId":"client-1","courseId":"crs-002","titleRu":"Добро пожаловать в портал","titleEn":"Welcome to Portal","bodyRu":"# Портал клиента\n\nВаш личный кабинет...","durationMin":15,"audience":"client","orderIndex":1,"createdAt":"2024-07-01T00:00:00Z","updatedAt":"2025-01-05T00:00:00Z"},
    {"id":"les-007","clientId":"client-1","courseId":"crs-002","titleRu":"Просмотр отчетов","titleEn":"Viewing Reports","bodyRu":"# Отчеты\n\nКак найти и скачать...","durationMin":15,"audience":"client","orderIndex":2,"createdAt":"2024-07-01T00:00:00Z","updatedAt":"2025-01-05T00:00:00Z"},
    {"id":"les-008","clientId":"client-1","courseId":"crs-002","titleRu":"Запросы и сообщения","titleEn":"Requests and Messages","bodyRu":"# Коммуникация\n\nКак связаться...","durationMin":15,"audience":"client","orderIndex":3,"createdAt":"2024-07-01T00:00:00Z","updatedAt":"2025-01-05T00:00:00Z"},
    {"id":"les-009","clientId":"client-1","courseId":"crs-003","titleRu":"Основы KYC","titleEn":"KYC Basics","bodyRu":"# KYC\n\nKnow Your Customer...","durationMin":25,"audience":"staff","orderIndex":1,"createdAt":"2024-08-01T00:00:00Z","updatedAt":"2025-01-08T00:00:00Z"},
    {"id":"les-010","clientId":"client-1","courseId":"crs-003","titleRu":"AML скрининг","titleEn":"AML Screening","bodyRu":"# AML\n\nПроцедуры проверки...","durationMin":25,"audience":"staff","orderIndex":2,"createdAt":"2024-08-01T00:00:00Z","updatedAt":"2025-01-08T00:00:00Z"},
    {"id":"les-011","clientId":"client-1","courseId":"crs-003","titleRu":"Оценка рисков","titleEn":"Risk Assessment","bodyRu":"# Risk Scoring\n\nКак оценивать...","durationMin":20,"audience":"staff","orderIndex":3,"createdAt":"2024-08-01T00:00:00Z","updatedAt":"2025-01-08T00:00:00Z"},
    {"id":"les-012","clientId":"client-1","courseId":"crs-003","titleRu":"Документирование","titleEn":"Documentation","bodyRu":"# Документы\n\nЧто собирать...","durationMin":20,"quizJson":{"questions":[{"q":"Что требуется для KYC?","options":["Паспорт","Фото","Все перечисленное"],"correct":2}]},"audience":"staff","orderIndex":4,"createdAt":"2024-08-01T00:00:00Z","updatedAt":"2025-01-08T00:00:00Z"},
    {"id":"les-013","clientId":"client-1","courseId":"crs-004","titleRu":"Загрузка документов","titleEn":"Uploading Documents","bodyRu":"# Загрузка\n\nКак добавить...","durationMin":20,"audience":"both","orderIndex":1,"createdAt":"2024-09-01T00:00:00Z","updatedAt":"2025-01-03T00:00:00Z"},
    {"id":"les-014","clientId":"client-1","courseId":"crs-004","titleRu":"Версионирование","titleEn":"Versioning","bodyRu":"# Версии\n\nИстория изменений...","durationMin":20,"audience":"both","orderIndex":2,"createdAt":"2024-09-01T00:00:00Z","updatedAt":"2025-01-03T00:00:00Z"},
    {"id":"les-015","clientId":"client-1","courseId":"crs-004","titleRu":"Шаринг документов","titleEn":"Document Sharing","bodyRu":"# Шаринг\n\nКак поделиться...","durationMin":20,"audience":"both","orderIndex":3,"createdAt":"2024-09-01T00:00:00Z","updatedAt":"2025-01-03T00:00:00Z"},
    {"id":"les-016","clientId":"client-1","courseId":"crs-005","titleRu":"Основы безопасности","titleEn":"Security Basics","bodyRu":"# Безопасность\n\nОсновные принципы...","durationMin":15,"audience":"both","orderIndex":1,"createdAt":"2024-10-01T00:00:00Z","updatedAt":"2025-01-10T00:00:00Z"},
    {"id":"les-017","clientId":"client-1","courseId":"crs-005","titleRu":"Пароли и MFA","titleEn":"Passwords and MFA","bodyRu":"# Аутентификация\n\nКак защитить...","durationMin":20,"audience":"both","orderIndex":2,"createdAt":"2024-10-01T00:00:00Z","updatedAt":"2025-01-10T00:00:00Z"},
    {"id":"les-018","clientId":"client-1","courseId":"crs-005","titleRu":"Реагирование на инциденты","titleEn":"Incident Response","bodyRu":"# Инциденты\n\nЧто делать если...","durationMin":15,"quizJson":{"questions":[{"q":"Что делать при подозрении на взлом?","options":["Игнорировать","Сообщить в Security","Выключить компьютер"],"correct":1}]},"audience":"both","orderIndex":3,"createdAt":"2024-10-01T00:00:00Z","updatedAt":"2025-01-10T00:00:00Z"},
    {"id":"les-019","clientId":"client-1","courseId":"crs-006","titleRu":"Типы отчетов","titleEn":"Report Types","bodyRu":"# Отчеты\n\nВиды отчетов...","durationMin":20,"audience":"staff","orderIndex":1,"createdAt":"2024-11-01T00:00:00Z","updatedAt":"2025-01-05T00:00:00Z"},
    {"id":"les-020","clientId":"client-1","courseId":"crs-006","titleRu":"Создание пакетов","titleEn":"Creating Packages","bodyRu":"# Пакеты\n\nКак собрать...","durationMin":20,"audience":"staff","orderIndex":2,"createdAt":"2024-11-01T00:00:00Z","updatedAt":"2025-01-05T00:00:00Z"},
    {"id":"les-021","clientId":"client-1","courseId":"crs-006","titleRu":"Шаблоны отчетов","titleEn":"Report Templates","bodyRu":"# Шаблоны\n\nНастройка шаблонов...","durationMin":20,"audience":"staff","orderIndex":3,"createdAt":"2024-11-01T00:00:00Z","updatedAt":"2025-01-05T00:00:00Z"},
    {"id":"les-022","clientId":"client-1","courseId":"crs-006","titleRu":"Экспорт и доставка","titleEn":"Export and Delivery","bodyRu":"# Доставка\n\nКак отправить...","durationMin":20,"audience":"staff","orderIndex":4,"createdAt":"2024-11-01T00:00:00Z","updatedAt":"2025-01-05T00:00:00Z"},
    {"id":"les-023","clientId":"client-1","courseId":"crs-007","titleRu":"Что такое IPS","titleEn":"What is IPS","bodyRu":"# IPS\n\nИнвестиционная политика...","durationMin":25,"audience":"staff","orderIndex":1,"createdAt":"2024-12-01T00:00:00Z","updatedAt":"2025-01-08T00:00:00Z"},
    {"id":"les-024","clientId":"client-1","courseId":"crs-007","titleRu":"Ограничения и лимиты","titleEn":"Constraints and Limits","bodyRu":"# Ограничения\n\nТипы ограничений...","durationMin":25,"audience":"staff","orderIndex":2,"createdAt":"2024-12-01T00:00:00Z","updatedAt":"2025-01-08T00:00:00Z"},
    {"id":"les-025","clientId":"client-1","courseId":"crs-007","titleRu":"Мониторинг нарушений","titleEn":"Breach Monitoring","bodyRu":"# Нарушения\n\nКак отслеживать...","durationMin":20,"audience":"staff","orderIndex":3,"createdAt":"2024-12-01T00:00:00Z","updatedAt":"2025-01-08T00:00:00Z"},
    {"id":"les-026","clientId":"client-1","courseId":"crs-008","titleRu":"Tax Lots основы","titleEn":"Tax Lots Basics","bodyRu":"# Tax Lots\n\nЧто такое tax lot...","durationMin":25,"audience":"staff","orderIndex":1,"createdAt":"2024-12-15T00:00:00Z","updatedAt":"2025-01-10T00:00:00Z"},
    {"id":"les-027","clientId":"client-1","courseId":"crs-008","titleRu":"Tax Loss Harvesting","titleEn":"Tax Loss Harvesting","bodyRu":"# Harvesting\n\nСтратегия оптимизации...","durationMin":25,"audience":"staff","orderIndex":2,"createdAt":"2024-12-15T00:00:00Z","updatedAt":"2025-01-10T00:00:00Z"},
    {"id":"les-028","clientId":"client-1","courseId":"crs-008","titleRu":"Отчетность для налоговой","titleEn":"Tax Reporting","bodyRu":"# Отчетность\n\nПодготовка документов...","durationMin":25,"audience":"staff","orderIndex":3,"createdAt":"2024-12-15T00:00:00Z","updatedAt":"2025-01-10T00:00:00Z"},
    {"id":"les-029","clientId":"client-1","courseId":"crs-009","titleRu":"Типы трастов","titleEn":"Trust Types","bodyRu":"# Трасты\n\nRevocable vs Irrevocable...","durationMin":30,"audience":"staff","orderIndex":1,"createdAt":"2025-01-01T00:00:00Z","updatedAt":"2025-01-12T00:00:00Z"},
    {"id":"les-030","clientId":"client-1","courseId":"crs-009","titleRu":"Администрирование трастов","titleEn":"Trust Administration","bodyRu":"# Администрирование\n\nОбязанности trustee...","durationMin":30,"audience":"staff","orderIndex":2,"createdAt":"2025-01-01T00:00:00Z","updatedAt":"2025-01-12T00:00:00Z"},
    {"id":"les-031","clientId":"client-1","courseId":"crs-010","titleRu":"Prompt Engineering","titleEn":"Prompt Engineering","bodyRu":"# Prompts\n\nКак формулировать...","durationMin":20,"audience":"staff","orderIndex":1,"createdAt":"2025-01-05T00:00:00Z","updatedAt":"2025-01-15T00:00:00Z"},
    {"id":"les-032","clientId":"client-1","courseId":"crs-010","titleRu":"Интеграция AI в workflow","titleEn":"AI Workflow Integration","bodyRu":"# AI Workflow\n\nАвтоматизация с AI...","durationMin":20,"audience":"staff","orderIndex":2,"createdAt":"2025-01-05T00:00:00Z","updatedAt":"2025-01-15T00:00:00Z"},
    {"id":"les-033","clientId":"client-1","courseId":"crs-011","titleRu":"Метрики риска","titleEn":"Risk Metrics","bodyRu":"# Метрики\n\nVaR, Sharpe...","durationMin":25,"audience":"staff","orderIndex":1,"createdAt":"2024-11-15T00:00:00Z","updatedAt":"2025-01-08T00:00:00Z"},
    {"id":"les-034","clientId":"client-1","courseId":"crs-011","titleRu":"Алерты и пороги","titleEn":"Alerts and Thresholds","bodyRu":"# Алерты\n\nНастройка порогов...","durationMin":20,"audience":"staff","orderIndex":2,"createdAt":"2024-11-15T00:00:00Z","updatedAt":"2025-01-08T00:00:00Z"},
    {"id":"les-035","clientId":"client-1","courseId":"crs-011","titleRu":"Stress тестирование","titleEn":"Stress Testing","bodyRu":"# Stress Tests\n\nСценарии...","durationMin":20,"audience":"staff","orderIndex":3,"createdAt":"2024-11-15T00:00:00Z","updatedAt":"2025-01-08T00:00:00Z"}
  ],
  "kbChecklists": [
    {"id":"chk-001","clientId":"client-1","nameRu":"Онбординг нового сотрудника","nameEn":"New Employee Onboarding","descriptionRu":"Чек-лист для новых сотрудников MFO","roleTarget":"any","stepsJson":[{"id":"s1","titleRu":"Получить доступы к системам","required":true},{"id":"s2","titleRu":"Пройти курс онбординга","required":true},{"id":"s3","titleRu":"Настроить MFA","required":true},{"id":"s4","titleRu":"Ознакомиться с политиками","required":true},{"id":"s5","titleRu":"Встреча с руководителем","required":false}],"audience":"staff","enforceOrder":true,"status":"active","createdAt":"2024-06-01T00:00:00Z","updatedAt":"2025-01-10T00:00:00Z"},
    {"id":"chk-002","clientId":"client-1","nameRu":"Compliance onboarding","nameEn":"Compliance Onboarding","descriptionRu":"Для compliance officers","roleTarget":"compliance","stepsJson":[{"id":"s1","titleRu":"Изучить KYC процессы","required":true},{"id":"s2","titleRu":"Изучить AML процедуры","required":true},{"id":"s3","titleRu":"Пройти тест по compliance","required":true}],"audience":"staff","enforceOrder":false,"status":"active","createdAt":"2024-08-01T00:00:00Z","updatedAt":"2025-01-08T00:00:00Z"},
    {"id":"chk-003","clientId":"client-1","nameRu":"Security checklist","nameEn":"Security Checklist","descriptionRu":"Ежеквартальная проверка безопасности","roleTarget":"any","stepsJson":[{"id":"s1","titleRu":"Сменить пароль","required":true},{"id":"s2","titleRu":"Проверить активные сессии","required":true},{"id":"s3","titleRu":"Проверить доступы","required":true}],"audience":"staff","enforceOrder":false,"status":"active","createdAt":"2024-10-01T00:00:00Z","updatedAt":"2025-01-10T00:00:00Z"},
    {"id":"chk-004","clientId":"client-1","nameRu":"Онбординг клиента (Staff)","nameEn":"Client Onboarding (Staff)","descriptionRu":"Чек-лист для RM при онбординге клиента","roleTarget":"rm","stepsJson":[{"id":"s1","titleRu":"Собрать KYC документы","required":true},{"id":"s2","titleRu":"Провести скрининг","required":true},{"id":"s3","titleRu":"Создать кейс в системе","required":true},{"id":"s4","titleRu":"Назначить advisor","required":true},{"id":"s5","titleRu":"Подготовить IPS","required":true}],"audience":"staff","enforceOrder":true,"status":"active","createdAt":"2024-07-01T00:00:00Z","updatedAt":"2025-01-05T00:00:00Z"},
    {"id":"chk-005","clientId":"client-1","nameRu":"Ежемесячная сверка","nameEn":"Monthly Reconciliation","descriptionRu":"Чек-лист для operations","roleTarget":"operations","stepsJson":[{"id":"s1","titleRu":"Запустить импорт данных","required":true},{"id":"s2","titleRu":"Проверить расхождения","required":true},{"id":"s3","titleRu":"Разрешить breaks","required":true},{"id":"s4","titleRu":"Подписать отчет","required":true}],"audience":"staff","enforceOrder":true,"status":"active","createdAt":"2024-09-01T00:00:00Z","updatedAt":"2025-01-12T00:00:00Z"},
    {"id":"chk-006","clientId":"client-1","nameRu":"Квартальный отчет","nameEn":"Quarterly Report","descriptionRu":"Подготовка квартального отчета","roleTarget":"operations","stepsJson":[{"id":"s1","titleRu":"Собрать данные по портфелям","required":true},{"id":"s2","titleRu":"Проверить performance","required":true},{"id":"s3","titleRu":"Сгенерировать пакеты","required":true},{"id":"s4","titleRu":"Review качества","required":true},{"id":"s5","titleRu":"Отправить клиентам","required":true}],"audience":"staff","enforceOrder":true,"status":"active","createdAt":"2024-11-01T00:00:00Z","updatedAt":"2025-01-08T00:00:00Z"},
    {"id":"chk-007","clientId":"client-1","nameRu":"Начало работы с порталом","nameEn":"Portal Getting Started","descriptionRu":"Для новых клиентов","roleTarget":"client","stepsJson":[{"id":"s1","titleRu":"Войти в портал","required":true},{"id":"s2","titleRu":"Настроить профиль","required":true},{"id":"s3","titleRu":"Просмотреть отчеты","required":false}],"audience":"client","enforceOrder":false,"status":"active","createdAt":"2024-07-15T00:00:00Z","updatedAt":"2025-01-05T00:00:00Z"},
    {"id":"chk-008","clientId":"client-1","nameRu":"Tax season prep","nameEn":"Tax Season Preparation","descriptionRu":"Подготовка к налоговому сезону","roleTarget":"operations","stepsJson":[{"id":"s1","titleRu":"Проверить tax lots","required":true},{"id":"s2","titleRu":"Сгенерировать отчеты","required":true},{"id":"s3","titleRu":"Отправить advisor packs","required":true}],"audience":"staff","enforceOrder":true,"status":"active","createdAt":"2024-12-01T00:00:00Z","updatedAt":"2025-01-10T00:00:00Z"},
    {"id":"chk-009","clientId":"client-1","nameRu":"IPS Review","nameEn":"IPS Review","descriptionRu":"Ежегодный пересмотр IPS","roleTarget":"rm","stepsJson":[{"id":"s1","titleRu":"Собрать текущий IPS","required":true},{"id":"s2","titleRu":"Проанализировать breaches","required":true},{"id":"s3","titleRu":"Подготовить предложения","required":true},{"id":"s4","titleRu":"Встреча с клиентом","required":true}],"audience":"staff","enforceOrder":true,"status":"active","createdAt":"2024-12-15T00:00:00Z","updatedAt":"2025-01-08T00:00:00Z"},
    {"id":"chk-010","clientId":"client-1","nameRu":"Incident response","nameEn":"Incident Response","descriptionRu":"При security инциденте","roleTarget":"admin","stepsJson":[{"id":"s1","titleRu":"Изолировать угрозу","required":true},{"id":"s2","titleRu":"Уведомить руководство","required":true},{"id":"s3","titleRu":"Задокументировать","required":true},{"id":"s4","titleRu":"Провести анализ","required":true}],"audience":"staff","enforceOrder":true,"status":"active","createdAt":"2025-01-01T00:00:00Z","updatedAt":"2025-01-12T00:00:00Z"},
    {"id":"chk-011","clientId":"client-1","nameRu":"Data quality check","nameEn":"Data Quality Check","descriptionRu":"Проверка качества данных","roleTarget":"operations","stepsJson":[{"id":"s1","titleRu":"Запустить DQ правила","required":true},{"id":"s2","titleRu":"Проверить исключения","required":true},{"id":"s3","titleRu":"Исправить ошибки","required":true}],"audience":"staff","enforceOrder":false,"status":"active","createdAt":"2024-10-15T00:00:00Z","updatedAt":"2025-01-05T00:00:00Z"},
    {"id":"chk-012","clientId":"client-1","nameRu":"Fee billing cycle","nameEn":"Fee Billing Cycle","descriptionRu":"Процесс выставления счетов","roleTarget":"operations","stepsJson":[{"id":"s1","titleRu":"Рассчитать fees","required":true},{"id":"s2","titleRu":"Проверить контракты","required":true},{"id":"s3","titleRu":"Сгенерировать invoices","required":true},{"id":"s4","titleRu":"Отправить клиентам","required":true}],"audience":"staff","enforceOrder":true,"status":"active","createdAt":"2024-11-15T00:00:00Z","updatedAt":"2025-01-10T00:00:00Z"},
    {"id":"chk-013","clientId":"client-1","nameRu":"Client review meeting","nameEn":"Client Review Meeting","descriptionRu":"Подготовка к встрече с клиентом","roleTarget":"rm","stepsJson":[{"id":"s1","titleRu":"Подготовить презентацию","required":true},{"id":"s2","titleRu":"Собрать performance данные","required":true},{"id":"s3","titleRu":"Проверить IPS статус","required":true}],"audience":"staff","enforceOrder":false,"status":"active","createdAt":"2024-08-15T00:00:00Z","updatedAt":"2025-01-08T00:00:00Z"},
    {"id":"chk-014","clientId":"client-1","nameRu":"Year-end closing","nameEn":"Year-End Closing","descriptionRu":"Закрытие года","roleTarget":"operations","stepsJson":[{"id":"s1","titleRu":"Финальная сверка","required":true},{"id":"s2","titleRu":"Закрыть периоды","required":true},{"id":"s3","titleRu":"Архивировать документы","required":true},{"id":"s4","titleRu":"Подготовить annual reports","required":true}],"audience":"staff","enforceOrder":true,"status":"active","createdAt":"2024-12-20T00:00:00Z","updatedAt":"2025-01-12T00:00:00Z"},
    {"id":"chk-015","clientId":"client-1","nameRu":"API integration setup","nameEn":"API Integration Setup","descriptionRu":"Настройка новой интеграции","roleTarget":"admin","stepsJson":[{"id":"s1","titleRu":"Создать API ключи","required":true},{"id":"s2","titleRu":"Настроить webhooks","required":true},{"id":"s3","titleRu":"Протестировать","required":true}],"audience":"staff","enforceOrder":true,"status":"active","createdAt":"2024-09-15T00:00:00Z","updatedAt":"2025-01-05T00:00:00Z"},
    {"id":"chk-016","clientId":"client-1","nameRu":"Черновик чек-листа","nameEn":"Draft Checklist","descriptionRu":"В разработке","roleTarget":"any","stepsJson":[],"audience":"staff","enforceOrder":false,"status":"draft","createdAt":"2025-01-10T00:00:00Z","updatedAt":"2025-01-15T00:00:00Z"},
    {"id":"chk-017","clientId":"client-1","nameRu":"Committee meeting prep","nameEn":"Committee Meeting Prep","descriptionRu":"Подготовка к заседанию комитета","roleTarget":"compliance","stepsJson":[{"id":"s1","titleRu":"Собрать agenda","required":true},{"id":"s2","titleRu":"Подготовить материалы","required":true},{"id":"s3","titleRu":"Разослать приглашения","required":true}],"audience":"staff","enforceOrder":true,"status":"active","createdAt":"2024-10-01T00:00:00Z","updatedAt":"2025-01-08T00:00:00Z"},
    {"id":"chk-018","clientId":"client-1","nameRu":"Trust distribution","nameEn":"Trust Distribution","descriptionRu":"Процесс распределения из траста","roleTarget":"operations","stepsJson":[{"id":"s1","titleRu":"Проверить полномочия","required":true},{"id":"s2","titleRu":"Получить согласование","required":true},{"id":"s3","titleRu":"Выполнить перевод","required":true},{"id":"s4","titleRu":"Задокументировать","required":true}],"audience":"staff","enforceOrder":true,"status":"active","createdAt":"2025-01-05T00:00:00Z","updatedAt":"2025-01-12T00:00:00Z"}
  ],
  "kbChecklistRuns": [
    {"id":"run-001","clientId":"client-1","checklistId":"chk-001","userId":"user-3","stepStatesJson":[{"stepId":"s1","completed":true,"completedAt":"2025-01-10T10:00:00Z"},{"stepId":"s2","completed":true,"completedAt":"2025-01-11T14:00:00Z"},{"stepId":"s3","completed":true,"completedAt":"2025-01-12T09:00:00Z"},{"stepId":"s4","completed":false},{"stepId":"s5","completed":false}],"completionPct":60,"status":"in_progress","startedAt":"2025-01-10T09:00:00Z"},
    {"id":"run-002","clientId":"client-1","checklistId":"chk-001","userId":"user-4","stepStatesJson":[{"stepId":"s1","completed":true,"completedAt":"2025-01-05T10:00:00Z"},{"stepId":"s2","completed":true,"completedAt":"2025-01-06T14:00:00Z"},{"stepId":"s3","completed":true,"completedAt":"2025-01-07T09:00:00Z"},{"stepId":"s4","completed":true,"completedAt":"2025-01-08T11:00:00Z"},{"stepId":"s5","completed":true,"completedAt":"2025-01-09T15:00:00Z"}],"completionPct":100,"status":"completed","startedAt":"2025-01-05T09:00:00Z","completedAt":"2025-01-09T15:00:00Z"},
    {"id":"run-003","clientId":"client-1","checklistId":"chk-002","userId":"user-5","stepStatesJson":[{"stepId":"s1","completed":true,"completedAt":"2025-01-12T10:00:00Z"},{"stepId":"s2","completed":true,"completedAt":"2025-01-13T11:00:00Z"},{"stepId":"s3","completed":false}],"completionPct":66,"status":"in_progress","startedAt":"2025-01-12T09:00:00Z"},
    {"id":"run-004","clientId":"client-1","checklistId":"chk-003","userId":"user-1","stepStatesJson":[{"stepId":"s1","completed":true,"completedAt":"2025-01-01T10:00:00Z"},{"stepId":"s2","completed":true,"completedAt":"2025-01-01T11:00:00Z"},{"stepId":"s3","completed":true,"completedAt":"2025-01-01T12:00:00Z"}],"completionPct":100,"status":"completed","startedAt":"2025-01-01T09:00:00Z","completedAt":"2025-01-01T12:00:00Z"},
    {"id":"run-005","clientId":"client-1","checklistId":"chk-004","userId":"user-2","stepStatesJson":[{"stepId":"s1","completed":true,"completedAt":"2025-01-08T10:00:00Z"},{"stepId":"s2","completed":true,"completedAt":"2025-01-09T14:00:00Z"},{"stepId":"s3","completed":true,"completedAt":"2025-01-10T09:00:00Z"},{"stepId":"s4","completed":false},{"stepId":"s5","completed":false}],"completionPct":60,"status":"in_progress","startedAt":"2025-01-08T09:00:00Z"},
    {"id":"run-006","clientId":"client-1","checklistId":"chk-005","userId":"user-1","stepStatesJson":[{"stepId":"s1","completed":true,"completedAt":"2025-01-02T10:00:00Z"},{"stepId":"s2","completed":true,"completedAt":"2025-01-02T14:00:00Z"},{"stepId":"s3","completed":true,"completedAt":"2025-01-03T09:00:00Z"},{"stepId":"s4","completed":true,"completedAt":"2025-01-03T16:00:00Z"}],"completionPct":100,"status":"completed","startedAt":"2025-01-02T09:00:00Z","completedAt":"2025-01-03T16:00:00Z"},
    {"id":"run-007","clientId":"client-1","checklistId":"chk-006","userId":"user-1","stepStatesJson":[{"stepId":"s1","completed":true,"completedAt":"2025-01-10T10:00:00Z"},{"stepId":"s2","completed":true,"completedAt":"2025-01-11T11:00:00Z"},{"stepId":"s3","completed":false},{"stepId":"s4","completed":false},{"stepId":"s5","completed":false}],"completionPct":40,"status":"in_progress","startedAt":"2025-01-10T09:00:00Z"},
    {"id":"run-008","clientId":"client-1","checklistId":"chk-007","userId":"user-10","stepStatesJson":[{"stepId":"s1","completed":true,"completedAt":"2025-01-05T10:00:00Z"},{"stepId":"s2","completed":true,"completedAt":"2025-01-05T11:00:00Z"},{"stepId":"s3","completed":true,"completedAt":"2025-01-06T09:00:00Z"}],"completionPct":100,"status":"completed","startedAt":"2025-01-05T09:00:00Z","completedAt":"2025-01-06T09:00:00Z"},
    {"id":"run-009","clientId":"client-1","checklistId":"chk-008","userId":"user-1","stepStatesJson":[{"stepId":"s1","completed":true,"completedAt":"2025-01-08T10:00:00Z"},{"stepId":"s2","completed":false},{"stepId":"s3","completed":false}],"completionPct":33,"status":"in_progress","startedAt":"2025-01-08T09:00:00Z"},
    {"id":"run-010","clientId":"client-1","checklistId":"chk-009","userId":"user-2","stepStatesJson":[{"stepId":"s1","completed":true,"completedAt":"2025-01-12T10:00:00Z"},{"stepId":"s2","completed":true,"completedAt":"2025-01-13T11:00:00Z"},{"stepId":"s3","completed":false},{"stepId":"s4","completed":false}],"completionPct":50,"status":"in_progress","startedAt":"2025-01-12T09:00:00Z"},
    {"id":"run-011","clientId":"client-1","checklistId":"chk-011","userId":"user-1","stepStatesJson":[{"stepId":"s1","completed":true,"completedAt":"2025-01-14T10:00:00Z"},{"stepId":"s2","completed":true,"completedAt":"2025-01-14T14:00:00Z"},{"stepId":"s3","completed":false}],"completionPct":66,"status":"in_progress","startedAt":"2025-01-14T09:00:00Z"},
    {"id":"run-012","clientId":"client-1","checklistId":"chk-012","userId":"user-1","stepStatesJson":[{"stepId":"s1","completed":true,"completedAt":"2025-01-10T10:00:00Z"},{"stepId":"s2","completed":true,"completedAt":"2025-01-10T14:00:00Z"},{"stepId":"s3","completed":true,"completedAt":"2025-01-11T09:00:00Z"},{"stepId":"s4","completed":true,"completedAt":"2025-01-11T16:00:00Z"}],"completionPct":100,"status":"completed","startedAt":"2025-01-10T09:00:00Z","completedAt":"2025-01-11T16:00:00Z"},
    {"id":"run-013","clientId":"client-1","checklistId":"chk-013","userId":"user-2","stepStatesJson":[{"stepId":"s1","completed":true,"completedAt":"2025-01-15T10:00:00Z"},{"stepId":"s2","completed":false},{"stepId":"s3","completed":false}],"completionPct":33,"status":"in_progress","startedAt":"2025-01-15T09:00:00Z"},
    {"id":"run-014","clientId":"client-1","checklistId":"chk-014","userId":"user-1","stepStatesJson":[{"stepId":"s1","completed":true,"completedAt":"2024-12-28T10:00:00Z"},{"stepId":"s2","completed":true,"completedAt":"2024-12-29T11:00:00Z"},{"stepId":"s3","completed":true,"completedAt":"2024-12-30T09:00:00Z"},{"stepId":"s4","completed":true,"completedAt":"2024-12-31T16:00:00Z"}],"completionPct":100,"status":"completed","startedAt":"2024-12-28T09:00:00Z","completedAt":"2024-12-31T16:00:00Z"},
    {"id":"run-015","clientId":"client-1","checklistId":"chk-003","userId":"user-2","stepStatesJson":[{"stepId":"s1","completed":true,"completedAt":"2025-01-01T10:00:00Z"},{"stepId":"s2","completed":true,"completedAt":"2025-01-01T11:00:00Z"},{"stepId":"s3","completed":true,"completedAt":"2025-01-01T12:00:00Z"}],"completionPct":100,"status":"completed","startedAt":"2025-01-01T09:00:00Z","completedAt":"2025-01-01T12:00:00Z"},
    {"id":"run-016","clientId":"client-1","checklistId":"chk-017","userId":"user-5","stepStatesJson":[{"stepId":"s1","completed":true,"completedAt":"2025-01-13T10:00:00Z"},{"stepId":"s2","completed":true,"completedAt":"2025-01-14T11:00:00Z"},{"stepId":"s3","completed":false}],"completionPct":66,"status":"in_progress","startedAt":"2025-01-13T09:00:00Z"},
    {"id":"run-017","clientId":"client-1","checklistId":"chk-001","userId":"user-6","stepStatesJson":[{"stepId":"s1","completed":true,"completedAt":"2025-01-14T10:00:00Z"},{"stepId":"s2","completed":false},{"stepId":"s3","completed":false},{"stepId":"s4","completed":false},{"stepId":"s5","completed":false}],"completionPct":20,"status":"in_progress","startedAt":"2025-01-14T09:00:00Z"},
    {"id":"run-018","clientId":"client-1","checklistId":"chk-015","userId":"user-1","stepStatesJson":[{"stepId":"s1","completed":true,"completedAt":"2025-01-07T10:00:00Z"},{"stepId":"s2","completed":true,"completedAt":"2025-01-07T14:00:00Z"},{"stepId":"s3","completed":true,"completedAt":"2025-01-08T09:00:00Z"}],"completionPct":100,"status":"completed","startedAt":"2025-01-07T09:00:00Z","completedAt":"2025-01-08T09:00:00Z"},
    {"id":"run-019","clientId":"client-1","checklistId":"chk-018","userId":"user-1","stepStatesJson":[{"stepId":"s1","completed":true,"completedAt":"2025-01-12T10:00:00Z"},{"stepId":"s2","completed":true,"completedAt":"2025-01-13T11:00:00Z"},{"stepId":"s3","completed":false},{"stepId":"s4","completed":false}],"completionPct":50,"status":"in_progress","startedAt":"2025-01-12T09:00:00Z"},
    {"id":"run-020","clientId":"client-1","checklistId":"chk-004","userId":"user-2","stepStatesJson":[{"stepId":"s1","completed":true,"completedAt":"2024-12-15T10:00:00Z"},{"stepId":"s2","completed":true,"completedAt":"2024-12-16T14:00:00Z"},{"stepId":"s3","completed":true,"completedAt":"2024-12-17T09:00:00Z"},{"stepId":"s4","completed":true,"completedAt":"2024-12-18T11:00:00Z"},{"stepId":"s5","completed":true,"completedAt":"2024-12-19T15:00:00Z"}],"completionPct":100,"status":"completed","startedAt":"2024-12-15T09:00:00Z","completedAt":"2024-12-19T15:00:00Z"},
    {"id":"run-021","clientId":"client-1","checklistId":"chk-005","userId":"user-1","stepStatesJson":[{"stepId":"s1","completed":true,"completedAt":"2024-12-02T10:00:00Z"},{"stepId":"s2","completed":true,"completedAt":"2024-12-02T14:00:00Z"},{"stepId":"s3","completed":true,"completedAt":"2024-12-03T09:00:00Z"},{"stepId":"s4","completed":true,"completedAt":"2024-12-03T16:00:00Z"}],"completionPct":100,"status":"completed","startedAt":"2024-12-02T09:00:00Z","completedAt":"2024-12-03T16:00:00Z"},
    {"id":"run-022","clientId":"client-1","checklistId":"chk-007","userId":"user-11","stepStatesJson":[{"stepId":"s1","completed":true,"completedAt":"2025-01-10T10:00:00Z"},{"stepId":"s2","completed":false},{"stepId":"s3","completed":false}],"completionPct":33,"status":"in_progress","startedAt":"2025-01-10T09:00:00Z"},
    {"id":"run-023","clientId":"client-1","checklistId":"chk-006","userId":"user-1","stepStatesJson":[{"stepId":"s1","completed":true,"completedAt":"2024-10-05T10:00:00Z"},{"stepId":"s2","completed":true,"completedAt":"2024-10-06T11:00:00Z"},{"stepId":"s3","completed":true,"completedAt":"2024-10-07T09:00:00Z"},{"stepId":"s4","completed":true,"completedAt":"2024-10-08T14:00:00Z"},{"stepId":"s5","completed":true,"completedAt":"2024-10-09T16:00:00Z"}],"completionPct":100,"status":"completed","startedAt":"2024-10-05T09:00:00Z","completedAt":"2024-10-09T16:00:00Z"},
    {"id":"run-024","clientId":"client-1","checklistId":"chk-010","userId":"user-1","stepStatesJson":[{"stepId":"s1","completed":true,"completedAt":"2025-01-02T10:00:00Z"},{"stepId":"s2","completed":true,"completedAt":"2025-01-02T10:30:00Z"},{"stepId":"s3","completed":true,"completedAt":"2025-01-02T14:00:00Z"},{"stepId":"s4","completed":true,"completedAt":"2025-01-03T11:00:00Z"}],"completionPct":100,"status":"completed","startedAt":"2025-01-02T10:00:00Z","completedAt":"2025-01-03T11:00:00Z"}
  ],
  "kbFaq": [
    {"id":"faq-001","clientId":"client-1","questionRu":"Как сбросить пароль?","questionEn":"How to reset password?","answerRu":"Нажмите 'Забыли пароль' на странице входа...","answerEn":"Click 'Forgot password' on login page...","tagsJson":["security","onboarding"],"audience":"both","categoryKey":"security","orderIndex":1,"viewCount":234,"createdAt":"2024-06-01T00:00:00Z","updatedAt":"2025-01-10T00:00:00Z"},
    {"id":"faq-002","clientId":"client-1","questionRu":"Как настроить двухфакторную аутентификацию?","questionEn":"How to set up 2FA?","answerRu":"Перейдите в Настройки > Безопасность > MFA...","answerEn":"Go to Settings > Security > MFA...","tagsJson":["security"],"audience":"both","categoryKey":"security","orderIndex":2,"viewCount":189,"createdAt":"2024-06-01T00:00:00Z","updatedAt":"2025-01-08T00:00:00Z"},
    {"id":"faq-003","clientId":"client-1","questionRu":"Где найти мои отчеты?","questionEn":"Where to find my reports?","answerRu":"Отчеты доступны в разделе Отчеты...","answerEn":"Reports are available in Reports section...","tagsJson":["reporting"],"audience":"both","categoryKey":"reporting","orderIndex":1,"viewCount":312,"createdAt":"2024-06-15T00:00:00Z","updatedAt":"2025-01-05T00:00:00Z"},
    {"id":"faq-004","clientId":"client-1","questionRu":"Как загрузить документ?","questionEn":"How to upload a document?","answerRu":"В разделе Документы нажмите 'Загрузить'...","answerEn":"In Documents section click 'Upload'...","tagsJson":["documents"],"audience":"both","categoryKey":"documents","orderIndex":1,"viewCount":267,"createdAt":"2024-07-01T00:00:00Z","updatedAt":"2025-01-03T00:00:00Z"},
    {"id":"faq-005","clientId":"client-1","questionRu":"Что такое IPS?","questionEn":"What is IPS?","answerRu":"IPS (Investment Policy Statement) - документ...","answerEn":"IPS (Investment Policy Statement) is a document...","tagsJson":["ips","investment"],"audience":"both","categoryKey":"investment","orderIndex":1,"viewCount":156,"createdAt":"2024-07-15T00:00:00Z","updatedAt":"2024-12-20T00:00:00Z"},
    {"id":"faq-006","clientId":"client-1","questionRu":"Как связаться с advisor?","questionEn":"How to contact advisor?","answerRu":"Используйте раздел Сообщения...","answerEn":"Use Messages section...","tagsJson":["client-portal"],"audience":"client","categoryKey":"communication","orderIndex":1,"viewCount":198,"createdAt":"2024-08-01T00:00:00Z","updatedAt":"2025-01-10T00:00:00Z"},
    {"id":"faq-007","clientId":"client-1","questionRu":"Как часто обновляются данные?","questionEn":"How often is data updated?","answerRu":"Данные синхронизируются ежедневно...","answerEn":"Data is synchronized daily...","tagsJson":["data","integration"],"audience":"both","categoryKey":"data","orderIndex":1,"viewCount":145,"createdAt":"2024-08-15T00:00:00Z","updatedAt":"2025-01-08T00:00:00Z"},
    {"id":"faq-008","clientId":"client-1","questionRu":"Что делать при расхождении данных?","questionEn":"What to do if data doesn't match?","answerRu":"Сообщите в Operations через задачу...","answerEn":"Report to Operations via task...","tagsJson":["reconciliation","data"],"audience":"both","categoryKey":"data","orderIndex":2,"viewCount":89,"createdAt":"2024-09-01T00:00:00Z","updatedAt":"2025-01-05T00:00:00Z"},
    {"id":"faq-009","clientId":"client-1","questionRu":"Как работает tax loss harvesting?","questionEn":"How does tax loss harvesting work?","answerRu":"Tax loss harvesting - стратегия оптимизации...","answerEn":"Tax loss harvesting is an optimization strategy...","tagsJson":["tax"],"audience":"both","categoryKey":"tax","orderIndex":1,"viewCount":112,"createdAt":"2024-09-15T00:00:00Z","updatedAt":"2025-01-10T00:00:00Z"},
    {"id":"faq-010","clientId":"client-1","questionRu":"Как добавить бенефициара траста?","questionEn":"How to add trust beneficiary?","answerRu":"В разделе Трасты выберите траст...","answerEn":"In Trusts section select trust...","tagsJson":["trust"],"audience":"staff","categoryKey":"trust","orderIndex":1,"viewCount":67,"createdAt":"2024-10-01T00:00:00Z","updatedAt":"2025-01-08T00:00:00Z"},
    {"id":"faq-011","clientId":"client-1","questionRu":"Какие форматы экспорта поддерживаются?","questionEn":"What export formats are supported?","answerRu":"Поддерживаются PDF, Excel, CSV...","answerEn":"Supported: PDF, Excel, CSV...","tagsJson":["export","reporting"],"audience":"both","categoryKey":"reporting","orderIndex":2,"viewCount":134,"createdAt":"2024-10-15T00:00:00Z","updatedAt":"2025-01-05T00:00:00Z"},
    {"id":"faq-012","clientId":"client-1","questionRu":"Как настроить уведомления?","questionEn":"How to configure notifications?","answerRu":"В Настройках выберите Уведомления...","answerEn":"In Settings select Notifications...","tagsJson":["notification"],"audience":"both","categoryKey":"settings","orderIndex":1,"viewCount":178,"createdAt":"2024-11-01T00:00:00Z","updatedAt":"2025-01-10T00:00:00Z"},
    {"id":"faq-013","clientId":"client-1","questionRu":"Что означают статусы задач?","questionEn":"What do task statuses mean?","answerRu":"Open - новая, In Progress - в работе...","answerEn":"Open - new, In Progress - working...","tagsJson":["workflow"],"audience":"both","categoryKey":"workflow","orderIndex":1,"viewCount":145,"createdAt":"2024-11-15T00:00:00Z","updatedAt":"2025-01-08T00:00:00Z"},
    {"id":"faq-014","clientId":"client-1","questionRu":"Как запросить изменение IPS?","questionEn":"How to request IPS change?","answerRu":"Создайте запрос в разделе IPS...","answerEn":"Create request in IPS section...","tagsJson":["ips"],"audience":"both","categoryKey":"investment","orderIndex":2,"viewCount":78,"createdAt":"2024-12-01T00:00:00Z","updatedAt":"2025-01-05T00:00:00Z"},
    {"id":"faq-015","clientId":"client-1","questionRu":"Как работает AI Copilot?","questionEn":"How does AI Copilot work?","answerRu":"AI Copilot анализирует данные и помогает...","answerEn":"AI Copilot analyzes data and helps...","tagsJson":["ai","copilot"],"audience":"both","categoryKey":"ai","orderIndex":1,"viewCount":201,"createdAt":"2024-12-15T00:00:00Z","updatedAt":"2025-01-12T00:00:00Z"},
    {"id":"faq-016","clientId":"client-1","questionRu":"Какие данные видит AI?","questionEn":"What data does AI see?","answerRu":"AI имеет доступ только к данным в scope...","answerEn":"AI only has access to data in scope...","tagsJson":["ai","privacy"],"audience":"both","categoryKey":"ai","orderIndex":2,"viewCount":156,"createdAt":"2025-01-01T00:00:00Z","updatedAt":"2025-01-10T00:00:00Z"},
    {"id":"faq-017","clientId":"client-1","questionRu":"Как поделиться документом?","questionEn":"How to share a document?","answerRu":"Выберите документ, нажмите Share...","answerEn":"Select document, click Share...","tagsJson":["documents"],"audience":"both","categoryKey":"documents","orderIndex":2,"viewCount":189,"createdAt":"2024-07-20T00:00:00Z","updatedAt":"2025-01-08T00:00:00Z"},
    {"id":"faq-018","clientId":"client-1","questionRu":"Что такое evidence pack?","questionEn":"What is evidence pack?","answerRu":"Evidence pack - пакет документов для аудита...","answerEn":"Evidence pack is a document package for audit...","tagsJson":["documents","compliance"],"audience":"staff","categoryKey":"documents","orderIndex":3,"viewCount":67,"createdAt":"2024-08-20T00:00:00Z","updatedAt":"2025-01-05T00:00:00Z"},
    {"id":"faq-019","clientId":"client-1","questionRu":"Как посмотреть историю изменений?","questionEn":"How to view change history?","answerRu":"В карточке объекта нажмите Audit Trail...","answerEn":"In object card click Audit Trail...","tagsJson":["audit"],"audience":"both","categoryKey":"audit","orderIndex":1,"viewCount":112,"createdAt":"2024-09-20T00:00:00Z","updatedAt":"2025-01-10T00:00:00Z"},
    {"id":"faq-020","clientId":"client-1","questionRu":"Как работает согласование платежей?","questionEn":"How does payment approval work?","answerRu":"При создании платежа выше порога...","answerEn":"When creating payment above threshold...","tagsJson":["approval","workflow"],"audience":"staff","categoryKey":"workflow","orderIndex":2,"viewCount":89,"createdAt":"2024-10-20T00:00:00Z","updatedAt":"2025-01-08T00:00:00Z"}
  ],
  "kbPolicies": [
    {"id":"pol-001","clientId":"client-1","titleRu":"Политика информационной безопасности","titleEn":"Information Security Policy","bodyRu":"# Политика ИБ\n\n## Цель\nОбеспечить защиту...","bodyEn":"# InfoSec Policy\n\n## Purpose\nEnsure protection...","categoryKey":"security","audience":"staff","version":"2.1","status":"active","requiresAck":true,"ackDeadlineDays":7,"createdAt":"2024-01-01T00:00:00Z","updatedAt":"2025-01-10T00:00:00Z"},
    {"id":"pol-002","clientId":"client-1","titleRu":"Политика обработки персональных данных","titleEn":"Data Privacy Policy","bodyRu":"# Персональные данные\n\n## Scope\nДанная политика...","bodyEn":"# Personal Data\n\n## Scope\nThis policy...","categoryKey":"data","audience":"both","version":"3.0","status":"active","requiresAck":true,"ackDeadlineDays":14,"createdAt":"2024-02-01T00:00:00Z","updatedAt":"2025-01-08T00:00:00Z"},
    {"id":"pol-003","clientId":"client-1","titleRu":"Политика AML/KYC","titleEn":"AML/KYC Policy","bodyRu":"# AML/KYC\n\n## Обязательства\nКомпания обязуется...","bodyEn":"# AML/KYC\n\n## Commitments\nCompany commits...","categoryKey":"compliance","audience":"staff","version":"4.2","status":"active","requiresAck":true,"ackDeadlineDays":7,"createdAt":"2024-03-01T00:00:00Z","updatedAt":"2025-01-05T00:00:00Z"},
    {"id":"pol-004","clientId":"client-1","titleRu":"Кодекс этики","titleEn":"Code of Ethics","bodyRu":"# Кодекс этики\n\n## Принципы\n1. Честность...","bodyEn":"# Code of Ethics\n\n## Principles\n1. Integrity...","categoryKey":"hr","audience":"staff","version":"1.5","status":"active","requiresAck":true,"ackDeadlineDays":30,"createdAt":"2024-04-01T00:00:00Z","updatedAt":"2024-12-20T00:00:00Z"},
    {"id":"pol-005","clientId":"client-1","titleRu":"Политика управления конфликтами интересов","titleEn":"Conflict of Interest Policy","bodyRu":"# Конфликты интересов\n\n## Определение\nКонфликт...","bodyEn":"# Conflicts of Interest\n\n## Definition\nConflict...","categoryKey":"compliance","audience":"staff","version":"2.0","status":"active","requiresAck":true,"ackDeadlineDays":14,"createdAt":"2024-05-01T00:00:00Z","updatedAt":"2025-01-10T00:00:00Z"},
    {"id":"pol-006","clientId":"client-1","titleRu":"Политика использования IT ресурсов","titleEn":"IT Resources Policy","bodyRu":"# IT Ресурсы\n\n## Правила\nСотрудники обязаны...","bodyEn":"# IT Resources\n\n## Rules\nEmployees must...","categoryKey":"security","audience":"staff","version":"1.8","status":"active","requiresAck":true,"ackDeadlineDays":7,"createdAt":"2024-06-01T00:00:00Z","updatedAt":"2025-01-08T00:00:00Z"},
    {"id":"pol-007","clientId":"client-1","titleRu":"Политика работы с клиентами","titleEn":"Client Handling Policy","bodyRu":"# Работа с клиентами\n\n## Стандарты\n1. Конфиденциальность...","bodyEn":"# Client Handling\n\n## Standards\n1. Confidentiality...","categoryKey":"operational","audience":"staff","version":"2.3","status":"active","requiresAck":true,"ackDeadlineDays":14,"createdAt":"2024-07-01T00:00:00Z","updatedAt":"2025-01-05T00:00:00Z"},
    {"id":"pol-008","clientId":"client-1","titleRu":"Политика удаленной работы","titleEn":"Remote Work Policy","bodyRu":"# Удаленная работа\n\n## Требования\nПри удаленной работе...","bodyEn":"# Remote Work\n\n## Requirements\nWhen working remotely...","categoryKey":"hr","audience":"staff","version":"1.2","status":"active","requiresAck":true,"ackDeadlineDays":7,"createdAt":"2024-08-01T00:00:00Z","updatedAt":"2025-01-10T00:00:00Z"},
    {"id":"pol-009","clientId":"client-1","titleRu":"Политика резервного копирования","titleEn":"Backup Policy","bodyRu":"# Резервное копирование\n\n## Процедуры\nДанные...","bodyEn":"# Backup\n\n## Procedures\nData...","categoryKey":"security","audience":"staff","version":"3.1","status":"active","requiresAck":false,"createdAt":"2024-09-01T00:00:00Z","updatedAt":"2025-01-08T00:00:00Z"},
    {"id":"pol-010","clientId":"client-1","titleRu":"Политика реагирования на инциденты","titleEn":"Incident Response Policy","bodyRu":"# Инциденты\n\n## Процедура\nПри обнаружении...","bodyEn":"# Incidents\n\n## Procedure\nUpon detection...","categoryKey":"security","audience":"staff","version":"2.5","status":"active","requiresAck":true,"ackDeadlineDays":7,"createdAt":"2024-10-01T00:00:00Z","updatedAt":"2025-01-05T00:00:00Z"},
    {"id":"pol-011","clientId":"client-1","titleRu":"Условия использования портала","titleEn":"Portal Terms of Use","bodyRu":"# Условия использования\n\n## Принятие\nИспользуя портал...","bodyEn":"# Terms of Use\n\n## Acceptance\nBy using portal...","categoryKey":"operational","audience":"client","version":"1.0","status":"active","requiresAck":true,"ackDeadlineDays":0,"createdAt":"2024-11-01T00:00:00Z","updatedAt":"2025-01-10T00:00:00Z"},
    {"id":"pol-012","clientId":"client-1","titleRu":"Политика хранения данных","titleEn":"Data Retention Policy","bodyRu":"# Хранение данных\n\n## Сроки\nДанные хранятся...","bodyEn":"# Data Retention\n\n## Periods\nData is stored...","categoryKey":"data","audience":"staff","version":"1.4","status":"active","requiresAck":false,"createdAt":"2024-12-01T00:00:00Z","updatedAt":"2025-01-08T00:00:00Z"},
    {"id":"pol-013","clientId":"client-1","titleRu":"Политика управления доступом","titleEn":"Access Control Policy","bodyRu":"# Управление доступом\n\n## Принципы\nMinimum privilege...","bodyEn":"# Access Control\n\n## Principles\nMinimum privilege...","categoryKey":"security","audience":"staff","version":"2.2","status":"active","requiresAck":true,"ackDeadlineDays":7,"createdAt":"2025-01-01T00:00:00Z","updatedAt":"2025-01-12T00:00:00Z"},
    {"id":"pol-014","clientId":"client-1","titleRu":"Черновик: Политика AI","titleEn":"Draft: AI Policy","bodyRu":"# AI Политика\n\n## В разработке...","bodyEn":"# AI Policy\n\n## In development...","categoryKey":"compliance","audience":"staff","version":"0.1","status":"draft","requiresAck":false,"createdAt":"2025-01-10T00:00:00Z","updatedAt":"2025-01-15T00:00:00Z"},
    {"id":"pol-015","clientId":"client-1","titleRu":"Политика физической безопасности","titleEn":"Physical Security Policy","bodyRu":"# Физическая безопасность\n\n## Доступ в офис...","bodyEn":"# Physical Security\n\n## Office access...","categoryKey":"security","audience":"staff","version":"1.1","status":"active","requiresAck":false,"createdAt":"2024-05-15T00:00:00Z","updatedAt":"2025-01-05T00:00:00Z"},
    {"id":"pol-016","clientId":"client-1","titleRu":"Политика социальных сетей","titleEn":"Social Media Policy","bodyRu":"# Социальные сети\n\n## Рекомендации\nПри публикации...","bodyEn":"# Social Media\n\n## Guidelines\nWhen posting...","categoryKey":"hr","audience":"staff","version":"1.0","status":"active","requiresAck":true,"ackDeadlineDays":14,"createdAt":"2024-06-15T00:00:00Z","updatedAt":"2025-01-10T00:00:00Z"}
  ]
}
